[
  {
    "Unnamed: 0":null,
    "空間數":null,
    "業者名稱":null,
    "門市電話":null,
    "業別":null,
    "地址":null,
    "友善物種":null,
    "入內規定":null,
    "提供寵物周邊服務":null,
    "環境服務":null
  },
  {
    "Unnamed: 0":"文山區",
    "空間數":1.0,
    "業者名稱":"月光賞茶故事館",
    "門市電話":"2936-1479",
    "業別":"餐飲業",
    "地址":"文山區指南路3段38弄25號",
    "友善物種":"犬 (大\/中\/小型)、貓",
    "入內規定":"可落地\n  需禮貌帶\/生理褲",
    "提供寵物周邊服務":"寵物奔跑空間\n  提供寵物飲水",
    "環境服務":"無"
  },
  {
    "Unnamed: 0":"文山區",
    "空間數":2.0,
    "業者名稱":"阿義師的大茶壺餐廳",
    "門市電話":"2939-5615",
    "業別":"餐飲業",
    "地址":"文山區指南路三段38巷37-1號",
    "友善物種":"犬 (大\/中\/小型)、貓、寵物都可以沒有限制",
    "入內規定":"推車、不影響其他客人都可以",
    "提供寵物周邊服務":"提供寵物飲水",
    "環境服務":"提供酒精或乾洗手"
  },
  {
    "Unnamed: 0":"文山區",
    "空間數":3.0,
    "業者名稱":"貓空閒 cat's café",
    "門市電話":"0953-304-776",
    "業別":"餐飲業",
    "地址":"文山區指南路三段33-37號間空地",
    "友善物種":"犬 (大\/中\/小型)、貓",
    "入內規定":"可落地，建議牽繩，畢竟流浪貓有野性",
    "提供寵物周邊服務":"提供寵物飲水",
    "環境服務":"提供酒精或乾洗手"
  },
  {
    "Unnamed: 0":"文山區",
    "空間數":4.0,
    "業者名稱":"貓空清泉廣場",
    "門市電話":"2938-3222",
    "業別":"餐飲業",
    "地址":"文山區指南路三段38巷33-1號(對面上方)",
    "友善物種":"犬(中\/小型)、貓",
    "入內規定":"可落地, 需繫繩",
    "提供寵物周邊服務":"提供寵物飲水",
    "環境服務":"無"
  },
  {
    "Unnamed: 0":"文山區",
    "空間數":5.0,
    "業者名稱":"FOOTER-景美店",
    "門市電話":"0961-068-993",
    "業別":"一般零售業",
    "地址":"文山區景後街119號1樓",
    "友善物種":"犬(小型)、貓",
    "入內規定":"須著禮貌帶\/生理褲才可落地或於提籠\/推車內才能進入",
    "提供寵物周邊服務":"提供寵物飲水(自來水)",
    "環境服務":"提供酒精或乾洗手"
  },
  {
    "Unnamed: 0":"文山區",
    "空間數":6.0,
    "業者名稱":"Purrson Bistro呼嚕小酒館",
    "門市電話":"2936-9172",
    "業別":"餐飲業",
    "地址":"文山區指南路二段106號",
    "友善物種":"犬 (大\/中\/小型)、貓",
    "入內規定":"可落地(寵物須固定於座位旁，如便溺需收清潔費，詳細規定請見店家臉書)",
    "提供寵物周邊服務":"提供寵物飲水",
    "環境服務":"提供酒精或乾洗手"
  },
  {
    "Unnamed: 0":"文山區",
    "空間數":7.0,
    "業者名稱":"正大休閒茶園",
    "門市電話":"2938-4060",
    "業別":"餐飲業",
    "地址":"文山區指南路三段38巷33-5號",
    "友善物種":"犬 (大\/中\/小型)、貓、鸚鵡",
    "入內規定":"可落地, 於提籠\/推車內才能進入, 盡量不影響其他客人即可",
    "提供寵物周邊服務":"提供寵物飲水(須自備容器)",
    "環境服務":"提供酒精或乾洗手, \n  設有寵物友善公約並張貼於明顯處"
  },
  {
    "Unnamed: 0":"文山區",
    "空間數":8.0,
    "業者名稱":"貓空 雙橡園茶坊",
    "門市電話":"2234-4917",
    "業別":"餐飲業",
    "地址":"文山區指南路三段38巷33-6號",
    "友善物種":"犬 (大\/中\/小型)",
    "入內規定":"可落地",
    "提供寵物周邊服務":"提供寵物飲水\n  提供狗便袋",
    "環境服務":"提供酒精或乾洗手"
  },
  {
    "Unnamed: 0":"文山區",
    "空間數":9.0,
    "業者名稱":"貓空龍門客棧",
    "門市電話":"2939-8865",
    "業別":"餐飲業",
    "地址":"文山區指南路三段38巷22-2號",
    "友善物種":"犬 (大\/中\/小型)、貓",
    "入內規定":"可落地",
    "提供寵物周邊服務":"提供寵物飲水",
    "環境服務":"提供酒精或乾洗手\n  協助清潔便溺物"
  },
  {
    "Unnamed: 0":"文山區",
    "空間數":10.0,
    "業者名稱":"邀月茶坊",
    "門市電話":"02-29392025",
    "業別":"餐飲業",
    "地址":"文山區指南路三段40巷6號",
    "友善物種":"犬 (大\/中\/小型)、貓",
    "入內規定":"可落地",
    "提供寵物周邊服務":"提供寵物飲水, 寵物奔跑空間",
    "環境服務":"提供酒精或乾洗手"
  },
  {
    "Unnamed: 0":"文山區",
    "空間數":11.0,
    "業者名稱":"創義麵 萬芳店",
    "門市電話":"02-29308181",
    "業別":"餐飲業",
    "地址":"文山區興隆路三段67號2樓",
    "友善物種":"犬 (大\/中\/小型)、貓",
    "入內規定":"可落地, 於提籠\/推車內能進入, 需全程繫牽繩",
    "提供寵物周邊服務":"提供寵物飲水, 寵物餐",
    "環境服務":"提供酒精或乾洗手"
  },
  {
    "Unnamed: 0":"文山區",
    "空間數":12.0,
    "業者名稱":"舒曼六號餐館 動物園政大店",
    "門市電話":"02-22341088",
    "業別":"餐飲業",
    "地址":"文山區萬壽路6號",
    "友善物種":"犬 (大\/中\/小型)、貓",
    "入內規定":"可落地, 需全程繫牽繩, 可落地不關籠,其他寵物也歡迎,不影響其他客人為原則",
    "提供寵物周邊服務":"提供寵物飲水",
    "環境服務":"提供酒精或乾洗手"
  },
  {
    "Unnamed: 0":"文山區",
    "空間數":13.0,
    "業者名稱":"飛起咖咖",
    "門市電話":"02-89352600",
    "業別":"餐飲業",
    "地址":"文山區景文街13-2號",
    "友善物種":"犬 (大\/中\/小型)、貓",
    "入內規定":"可落地, 需繫繩",
    "提供寵物周邊服務":"提供寵物飲水, 寵物零食、肉乾販售",
    "環境服務":"提供酒精或乾洗手, 提供狗便袋"
  },
  {
    "Unnamed: 0":"信義區",
    "空間數":1.0,
    "業者名稱":"Verona 創義廚房",
    "門市電話":"8789-8875",
    "業別":"餐飲業",
    "地址":"信義區莊敬路197巷6號",
    "友善物種":"犬 (大\/中\/小型)、貓",
    "入內規定":"可落地",
    "提供寵物周邊服務":"提供寵物專用水碗\n  提供寵物牽繩勾",
    "環境服務":"提供酒精或乾洗手"
  },
  {
    "Unnamed: 0":"信義區",
    "空間數":2.0,
    "業者名稱":"台北君悅酒店-寵物套房",
    "門市電話":"2720-1234",
    "業別":"住宿業",
    "地址":"信義區松壽路2號",
    "友善物種":"犬 (小型\/2500公克以下)",
    "入內規定":"於提籠或牽繩才能進入，\n  室內都不可落地，除非在套房裡面",
    "提供寵物周邊服務":"寵物客房：\n  1.寵物餐\n  2.寵物專用餐具\n  3.寵物臥床\n  4.尿布墊\n  5.寵物奔跑空間\n  6.寵物盥洗用品",
    "環境服務":"協助清潔便溺物(限寵物客房內)"
  },
  {
    "Unnamed: 0":"信義區",
    "空間數":3.0,
    "業者名稱":"大毛屋涮涮鍋",
    "門市電話":"2758-7878",
    "業別":"餐飲業",
    "地址":"忠孝東路4段559巷16弄21-1號",
    "友善物種":"犬 (大\/中\/小型)、貓、其他",
    "入內規定":"可落地",
    "提供寵物周邊服務":"寵物提供雞肉吃到飽服務",
    "環境服務":"無"
  },
  {
    "Unnamed: 0":"信義區",
    "空間數":4.0,
    "業者名稱":"吐司股長",
    "門市電話":"2764-9060",
    "業別":"餐飲業",
    "地址":"信義區忠孝東路四段553巷6弄8-1號",
    "友善物種":"犬 (大\/中\/小型)、貓",
    "入內規定":"沒有硬性規定",
    "提供寵物周邊服務":"提供寵物飲水",
    "環境服務":"飼主須自行清潔便溺物"
  },
  {
    "Unnamed: 0":"信義區",
    "空間數":5.0,
    "業者名稱":"加爾第咖啡莊敬店",
    "門市電話":"2345-1136",
    "業別":"餐飲業",
    "地址":"信義區吳興街269巷1弄21號",
    "友善物種":"犬 (大\/中\/小型)、貓",
    "入內規定":"可落地不可以到處亂跑\n  需禮貌帶\/生理褲或需繫牽繩、提籠",
    "提供寵物周邊服務":"提供寵物飲水",
    "環境服務":"提供酒精或乾洗手\n  提供寵物飲水"
  },
  {
    "Unnamed: 0":"信義區",
    "空間數":6.0,
    "業者名稱":"加爾第咖啡吳興店",
    "門市電話":"8786-9915",
    "業別":"餐飲業",
    "地址":"信義區吳興街600巷78號",
    "友善物種":"犬 (大\/中\/小型)、貓",
    "入內規定":"可落地不可以到處亂跑\n  需禮貌帶\/生理褲或需繫牽繩、提籠\n  最主要以牽繩為主",
    "提供寵物周邊服務":"提供寵物飲水",
    "環境服務":"提供酒精或乾洗手\n  提供狗便袋\n  提供寵物飲水"
  },
  {
    "Unnamed: 0":"信義區",
    "空間數":7.0,
    "業者名稱":"June Burge 啾漢堡",
    "門市電話":"2346-0898",
    "業別":"餐飲業",
    "地址":"信義區林口街82號",
    "友善物種":"犬 (大\/中\/小型)、貓、寵物都可",
    "入內規定":"可落地",
    "提供寵物周邊服務":"寵物餐 寵物專用餐具",
    "環境服務":"無"
  },
  {
    "Unnamed: 0":"信義區",
    "空間數":8.0,
    "業者名稱":"胖老爹台北松山店",
    "門市電話":"2726-6656",
    "業別":"餐飲業",
    "地址":"信義區松山路501號1樓",
    "友善物種":"都可以，沒有規定",
    "入內規定":"可落地",
    "提供寵物周邊服務":"提供寵物牽繩掛勾\n  提供防汙墊\n  提供寵物飲用水及零食",
    "環境服務":"提供酒精或乾洗手、狗便袋 協助清潔便溺物 \n  設有動物友善公約"
  },
  {
    "Unnamed: 0":"信義區",
    "空間數":9.0,
    "業者名稱":"榕 Xinyi",
    "門市電話":"2720-0026",
    "業別":"餐飲業",
    "地址":"信義區基隆路二段12號",
    "友善物種":"犬 (大\/中\/小型)、貓、爬蟲類、家畜類基本都可以",
    "入內規定":"可落地, 飼主必須要注意自家動物的行蹤以及有無亂大小便",
    "提供寵物周邊服務":"提供寵物飲水",
    "環境服務":"提供酒精或乾洗手"
  },
  {
    "Unnamed: 0":"信義區",
    "空間數":10.0,
    "業者名稱":"日日美髮廊",
    "門市電話":"2765-1837",
    "業別":"美容業",
    "地址":"信義區忠孝東路五段71巷3弄7號1樓",
    "友善物種":"犬 (大\/中\/小型)、貓",
    "入內規定":"可落地",
    "提供寵物周邊服務":"提供寵物飲水",
    "環境服務":"提供酒精或乾洗手"
  },
  {
    "Unnamed: 0":"信義區",
    "空間數":11.0,
    "業者名稱":"Lazzy cafe",
    "門市電話":"02-8780-0383",
    "業別":"餐飲業",
    "地址":"信義區光復南路419巷49號",
    "友善物種":"犬 (大\/中\/小型)、貓、爬蟲類、家畜類",
    "入內規定":"可落地",
    "提供寵物周邊服務":"提供寵物飲水,\n  販售禮貌帶\/生理褲,\n  寵物餐\n  寵物專用餐具\n  寵物床墊\n  寵物用品販售\n  寵物奔跑空間\n  寵物柵欄",
    "環境服務":"提供酒精或乾洗手"
  },
  {
    "Unnamed: 0":"信義區",
    "空間數":12.0,
    "業者名稱":"艾迪瓦屋",
    "門市電話":"2346-5395",
    "業別":"餐飲業",
    "地址":"信義區松德路227號1樓",
    "友善物種":"犬 (大\/中\/小型)、貓",
    "入內規定":"可落地, 以不影響他人為主",
    "提供寵物周邊服務":"提供寵物飲水, 自製雞胸肉乾",
    "環境服務":"提供酒精或乾洗手"
  },
  {
    "Unnamed: 0":"信義區",
    "空間數":13.0,
    "業者名稱":"創義麵 信義店",
    "門市電話":"02-87809559",
    "業別":"餐飲業",
    "地址":"信義區莊敬路327號",
    "友善物種":"犬 (大\/中\/小型)、貓",
    "入內規定":"可落地, 於提籠\/推車內能進入, 需全程繫牽繩",
    "提供寵物周邊服務":"提供寵物飲水, 寵物餐",
    "環境服務":"提供酒精或乾洗手"
  },
  {
    "Unnamed: 0":"信義區",
    "空間數":14.0,
    "業者名稱":"創義麵 松山店",
    "門市電話":"02-27487461",
    "業別":"餐飲業",
    "地址":"信義區松山路11號",
    "友善物種":"犬 (大\/中\/小型)、貓",
    "入內規定":"可落地, 於提籠\/推車內能進入, 需全程繫牽繩",
    "提供寵物周邊服務":"提供寵物飲水, 寵物餐",
    "環境服務":"提供酒精或乾洗手"
  },
  {
    "Unnamed: 0":"信義區",
    "空間數":15.0,
    "業者名稱":"PapàRoy義式手作料理",
    "門市電話":"2925-1968",
    "業別":"餐飲業",
    "地址":"信義區忠孝東路四段553巷16號1樓",
    "友善物種":"犬 (大\/中\/小型)、貓",
    "入內規定":"無特殊限制，但須以尊重其他客人用餐為前提，店家保留是否接待的權利",
    "提供寵物周邊服務":"提供寵物飲水, 寵物餐, 寵物專用餐具",
    "環境服務":"提供酒精或乾洗手"
  },
  {
    "Unnamed: 0":"信義區",
    "空間數":16.0,
    "業者名稱":"Smile dessert cafe 微點咖啡",
    "門市電話":"02-2767-6503",
    "業別":"餐飲業",
    "地址":"信義區永吉路30巷157弄7號1樓",
    "友善物種":null,
    "入內規定":"可落地, 以不影響他人為主",
    "提供寵物周邊服務":"提供寵物飲水",
    "環境服務":"提供酒精或乾洗手"
  },
  {
    "Unnamed: 0":"信義區",
    "空間數":17.0,
    "業者名稱":"PRESERVE",
    "門市電話":"02-22287888",
    "業別":"餐飲業",
    "地址":"信義區忠孝東路4段515號 D4 1008",
    "友善物種":"犬 (大\/中\/小型)、貓",
    "入內規定":"於提籠\/推車內能進入, 需全程繫牽繩",
    "提供寵物周邊服務":"可其他寵物交流",
    "環境服務":"提供酒精或乾洗手"
  },
  {
    "Unnamed: 0":"信義區",
    "空間數":18.0,
    "業者名稱":"TOK 盡興時光",
    "門市電話":"02-27656228",
    "業別":"餐飲業",
    "地址":"信義區忠孝東路四段515號 櫃號D_1002 TOK_大巨蛋店",
    "友善物種":"犬 (大\/中\/小型)、貓",
    "入內規定":"可落地",
    "提供寵物周邊服務":"提供寵物飲水",
    "環境服務":"提供酒精或乾洗手"
  },
  {
    "Unnamed: 0":"信義區",
    "空間數":19.0,
    "業者名稱":"大巨星港式餐酒館",
    "門市電話":"02-27771717",
    "業別":"餐飲業",
    "地址":"信義區忠孝東路四段515號D區1樓1021",
    "友善物種":"犬 (小型)、 貓",
    "入內規定":"於提籠\/推車內能進入, 一定要著禮貌帶\/生理褲, 需全程在提籠推車內",
    "提供寵物周邊服務":"無",
    "環境服務":"提供酒精或乾洗手"
  },
  {
    "Unnamed: 0":"信義區",
    "空間數":20.0,
    "業者名稱":"時時珈琲",
    "門市電話":"02-27653920",
    "業別":"餐飲業",
    "地址":"信義區忠孝東路五段71巷38號",
    "友善物種":"犬 (中\/小型)、貓",
    "入內規定":"可落地",
    "提供寵物周邊服務":"提供寵物飲水",
    "環境服務":"提供酒精或乾洗手"
  },
  {
    "Unnamed: 0":"信義區",
    "空間數":21.0,
    "業者名稱":"傑博士手機平板維修-信義店",
    "門市電話":"02-27942595",
    "業別":"手機維修",
    "地址":"信義區吳興街462號",
    "友善物種":"犬(中\/小型)、貓",
    "入內規定":"無限制, 可落地",
    "提供寵物周邊服務":"提供寵物飲水",
    "環境服務":"提供酒精或乾洗手, 提供狗便袋"
  },
  {
    "Unnamed: 0":"信義區",
    "空間數":22.0,
    "業者名稱":"MAHOME 畫畫咖啡廳",
    "門市電話":"0983-516-868",
    "業別":"餐飲業",
    "地址":"信義區松信路64號1樓",
    "友善物種":"犬(中\/小型)、貓",
    "入內規定":"無限制, 可落地, 於提籠\/推車內能進入, 一定要著禮貌帶\/生理\n 褲, 如沒穿也可,但希望飼主多注意可外出蹓大小便",
    "提供寵物周邊服務":"提供寵物飲水",
    "環境服務":"提供酒精或乾洗手, 提供狗便袋"
  },
  {
    "Unnamed: 0":"信義區",
    "空間數":23.0,
    "業者名稱":"The zoo 蔬食主義 vegan food and beverage",
    "門市電話":"02-6604-1108",
    "業別":"餐飲業",
    "地址":"信義區市民大道六段108號1樓",
    "友善物種":"犬(中\/小型)、貓",
    "入內規定":"可落地\n • 寵物如有習慣性噴尿做記號,請自備禮貌帶或向店家購買。\n • 如寵物有向其他動物做挑釁行為,飼主請自行管理。\n • 店家會隨機出動救援動物,如遇臨時狀況需要閉店,店家會提供尚在店內的顧客折價券補償。 \n • 請先詢問店家是否可摸店內動物。禁止隨意餵食、拍打、踢、抱、嚇 店內動物\n • 店內禁止喧嘩吵鬧避免造成動物情緒壓力 \n • 如寵物有隨意便溺之行為,請確保如廁後再入店內。",
    "提供寵物周邊服務":"提供寵物飲水, 販售禮貌帶\/生理褲, 寵物餐, 寵物專用餐具",
    "環境服務":"提供酒精或乾洗手, 提供狗便袋"
  },
  {
    "Unnamed: 0":"信義區",
    "空間數":24.0,
    "業者名稱":"日淬Sun Drip Coffee",
    "門市電話":"989297772",
    "業別":"餐飲業",
    "地址":"信義區富陽街22號",
    "友善物種":"犬 (大\/中\/小型)、貓",
    "入內規定":"無限制, 可落地, 於提籠\/推車內能進入, 一定要著禮貌帶\/生理\n 褲, 如沒穿也可,但希望飼主多注意可外出蹓大小便",
    "提供寵物周邊服務":"提供寵物飲水, 寵物奔跑空間",
    "環境服務":"提供酒精或乾洗手"
  },
  {
    "Unnamed: 0":"信義區",
    "空間數":25.0,
    "業者名稱":"Baganhood蔬食餐酒館",
    "門市電話":"02-37622557",
    "業別":"餐飲業",
    "地址":"信義區忠孝東路四段553巷46弄11號1樓",
    "友善物種":"犬 (大\/中\/小型)、貓",
    "入內規定":"可落地, 於提籠\/推車內能進入, 需全程繫牽繩",
    "提供寵物周邊服務":"提供寵物飲水",
    "環境服務":"提供酒精或乾洗手"
  },
  {
    "Unnamed: 0":"信義區",
    "空間數":26.0,
    "業者名稱":"SHUFFLE BRUNCH & BAR",
    "門市電話":"(02)2766-0081",
    "業別":"餐飲業",
    "地址":"信義區忠孝東路四段553巷46弄4號1樓",
    "友善物種":"犬 (大\/中\/小型)、貓",
    "入內規定":"可落地, 於提籠\/推車內能進入, 一定要著禮貌帶\/生理褲",
    "提供寵物周邊服務":"提供寵物飲水, 販售禮貌帶\/生理褲, 寵物餐, 寵物專用餐具",
    "環境服務":"提供酒精或乾洗手"
  },
  {
    "Unnamed: 0":"信義區",
    "空間數":27.0,
    "業者名稱":"米蘇之間早餐工坊",
    "門市電話":"227687040",
    "業別":"餐飲業",
    "地址":"台北市信義區永吉路189-1號",
    "友善物種":"家犬，大型(>23公斤), 家犬，中型(9-23公斤), 家犬，小型(<9公斤), 家貓",
    "入內規定":"無限制, 可落地, 需全程繫牽繩, 一定要著禮貌帶\/生理褲",
    "提供寵物周邊服務":"提供寵物飲水, 寵物餐, 寵物奔跑空間",
    "環境服務":"提供酒精或乾洗手, 提供狗便袋"
  },
  {
    "Unnamed: 0":"信義區",
    "空間數":28.0,
    "業者名稱":"Rainma Cafe",
    "門市電話":"227588914",
    "業別":"餐飲業",
    "地址":"台北市信義區光復南路447-24號",
    "友善物種":"家犬，大型(>23公斤), 家犬，中型(9-23公斤), 家犬，小型(<9公斤), 家貓",
    "入內規定":"可落地, 一定要著禮貌帶\/生理褲",
    "提供寵物周邊服務":"提供寵物飲水",
    "環境服務":"提供酒精或乾洗手, 提供狗便袋"
  },
  {
    "Unnamed: 0":"松山區",
    "空間數":1.0,
    "業者名稱":"小春日和寵物咖啡",
    "門市電話":"8787-6920",
    "業別":"餐飲業",
    "地址":"松山區延壽街361號1樓",
    "友善物種":"犬 (大\/中\/小型)、貓(不要昆蟲類都可以)",
    "入內規定":"可落地\n  需禮貌帶\/生理褲",
    "提供寵物周邊服務":"租借禮貌帶\/生理褲\n  寵物用品販售\n  防汙墊\n  寵物奔跑空間\n  寵物美容",
    "環境服務":"提供酒精或洗手乳\n  飼主須自己清理寵物排泄物(店內提供拖把及紙巾)"
  },
  {
    "Unnamed: 0":"松山區",
    "空間數":2.0,
    "業者名稱":"嶼人Café",
    "門市電話":"2748-0069",
    "業別":"餐飲業",
    "地址":"松山區南京東路五段250巷2弄39號右側",
    "友善物種":"犬 (大\/中\/小型)、貓",
    "入內規定":"可落地",
    "提供寵物周邊服務":"提供寵物飲水、寵物專用餐具",
    "環境服務":"提供酒精或乾洗手、狗便袋, 協助清潔便溺物"
  },
  {
    "Unnamed: 0":"松山區",
    "空間數":3.0,
    "業者名稱":"角落酒吧",
    "門市電話":"2765-1150",
    "業別":"餐飲業",
    "地址":"松山區健康路442號",
    "友善物種":"犬 (大\/中\/小型)、貓",
    "入內規定":"可落地",
    "提供寵物周邊服務":"提供寵物奔跑空間",
    "環境服務":"協助清潔便溺物"
  },
  {
    "Unnamed: 0":"松山區",
    "空間數":4.0,
    "業者名稱":"攝狗狗寵物寫真工坊",
    "門市電話":"2578-8809",
    "業別":"其他-寵物攝影",
    "地址":"松山區八德路4段38號",
    "友善物種":"犬 (大\/中\/小型)、貓(不要爬蟲類)",
    "入內規定":"可落地",
    "提供寵物周邊服務":"寵物飲水",
    "環境服務":"提供酒精或乾洗手\n  協助清潔便溺物"
  },
  {
    "Unnamed: 0":"松山區",
    "空間數":5.0,
    "業者名稱":"Remak髮型工作室",
    "門市電話":"2742-5568",
    "業別":"美容業",
    "地址":"松山區南京東路五段83號2樓",
    "友善物種":"犬 (大\/中\/小型)、貓",
    "入內規定":"可落地",
    "提供寵物周邊服務":"提供寵物飲水,寵物奔跑空間",
    "環境服務":"無"
  },
  {
    "Unnamed: 0":"松山區",
    "空間數":6.0,
    "業者名稱":"獺空間aotter space",
    "門市電話":"2747-8613",
    "業別":"餐飲業",
    "地址":"松山區光復北路95號1樓",
    "友善物種":"犬 (大\/中\/小型)、貓",
    "入內規定":"可落地",
    "提供寵物周邊服務":"提供寵物飲水, 防汙墊",
    "環境服務":"提供酒精或乾洗手"
  },
  {
    "Unnamed: 0":"松山區",
    "空間數":7.0,
    "業者名稱":"小朝日和",
    "門市電話":"0928-029-772",
    "業別":"餐飲業",
    "地址":"松山區八德路三段12巷5弄17號1樓",
    "友善物種":"犬 (大\/中\/小型)、貓",
    "入內規定":"可落地",
    "提供寵物周邊服務":"提供寵物飲水\n  寵物餐\n  寵物專用餐具",
    "環境服務":"提供酒精或乾洗手"
  },
  {
    "Unnamed: 0":"松山區",
    "空間數":8.0,
    "業者名稱":"夜酌居酒屋",
    "門市電話":"02-2577-7970",
    "業別":"餐飲業",
    "地址":"松山區市民大道四段147號1樓",
    "友善物種":"犬 (大\/中\/小型)",
    "入內規定":"可落地",
    "提供寵物周邊服務":"提供寵物飲水, 寵物餐",
    "環境服務":"提供酒精或乾洗手"
  },
  {
    "Unnamed: 0":"松山區",
    "空間數":9.0,
    "業者名稱":"方舟私藏空間",
    "門市電話":"2713-3006",
    "業別":"一般零售業",
    "地址":"松山區民生東路四段55巷18號一樓、B1",
    "友善物種":"犬 (大\/中\/小型)、貓",
    "入內規定":"可落地",
    "提供寵物周邊服務":"提供寵物飲水, 租借禮貌帶\/生理褲, 販售禮貌帶\/生理褲, 寵物餐, 寵物專用餐具, 寵物床墊, 寵物用品販售, 寵物牽繩掛勾, 防汙墊, 大型寵物運輸籠, 中型寵物運輸籠, 小型寵物運輸籠, 寵物奔跑空間, 寵物柵欄",
    "環境服務":"提供酒精或乾洗手"
  },
  {
    "Unnamed: 0":"松山區",
    "空間數":10.0,
    "業者名稱":"cafe BOMBOM",
    "門市電話":"2765-6601",
    "業別":"餐飲業",
    "地址":"松山區延壽街386號一樓",
    "友善物種":"犬 (大\/中\/小型)、貓",
    "入內規定":"可落地,需全程繫牽繩,一定要著禮貌帶\/生理褲",
    "提供寵物周邊服務":"提供寵物飲水, 防汙墊",
    "環境服務":"提供酒精或乾洗手"
  },
  {
    "Unnamed: 0":"松山區",
    "空間數":11.0,
    "業者名稱":"夏綠蒂 · 小私廚",
    "門市電話":"2713-4533",
    "業別":"餐飲業",
    "地址":"松山區敦化北路244巷37號",
    "友善物種":"犬 (中\/小型)、貓",
    "入內規定":"可落地,需全程繫牽繩",
    "提供寵物周邊服務":"提供寵物飲水, 寵物專用餐具",
    "環境服務":"提供酒精或乾洗手"
  },
  {
    "Unnamed: 0":"松山區",
    "空間數":12.0,
    "業者名稱":"Compas Pasta House 康帕斯義麵屋",
    "門市電話":"2570-0389",
    "業別":"餐飲業",
    "地址":"松山區八德路三段106巷69號",
    "友善物種":"犬 (小型)、貓",
    "入內規定":"可落地, 於提籠\/推車內能進入, 需全程繫牽繩",
    "提供寵物周邊服務":"提供寵物飲水",
    "環境服務":"提供酒精或乾洗手"
  },
  {
    "Unnamed: 0":"松山區",
    "空間數":13.0,
    "業者名稱":"他。植物咖啡",
    "門市電話":"02-2747-6058",
    "業別":"餐飲業",
    "地址":"松山區八德路四段245巷52弄29號1樓",
    "友善物種":"犬 (大\/中\/小型)、貓、其它",
    "入內規定":"無限制, 可落地",
    "提供寵物周邊服務":"提供寵物飲水, 販售禮貌帶\/生理褲, 寵物餐",
    "環境服務":"協助清潔便溺物"
  },
  {
    "Unnamed: 0":"松山區",
    "空間數":14.0,
    "業者名稱":"Olo cafe",
    "門市電話":"02-7742-0486",
    "業別":"餐飲業",
    "地址":"松山區南京東路五段97號B1",
    "友善物種":"犬 (大\/中\/小型)、貓、其它",
    "入內規定":"可落地, 於提籠\/推車內能進入, 需全程繫牽繩, 一定要著禮貌帶\/生理褲",
    "提供寵物周邊服務":"提供寵物飲水、寵物用品",
    "環境服務":"提供酒精或乾洗手, 協助清潔便溺物, 提供狗便袋"
  },
  {
    "Unnamed: 0":"松山區",
    "空間數":15.0,
    "業者名稱":"Cozy Quail",
    "門市電話":"0908-080-205",
    "業別":"餐飲業",
    "地址":"松山區敦化北路165巷15號1樓",
    "友善物種":"犬 (大\/中\/小型)、貓、其它",
    "入內規定":"可落地, 於提籠\/推車內能進入, 需全程繫牽繩,一定要著禮貌帶\/生理褲",
    "提供寵物周邊服務":"提供寵物飲水, 販售禮貌帶\/生理褲",
    "環境服務":"提供酒精或乾洗手, 協助清潔便溺物"
  },
  {
    "Unnamed: 0":"松山區",
    "空間數":16.0,
    "業者名稱":"劍潭榮宗麵線一延吉店",
    "門市電話":"02-25775252",
    "業別":"餐飲業",
    "地址":"松山區延吉街39-1號",
    "友善物種":"犬 (大\/中\/小型)、貓、其它",
    "入內規定":"無限制",
    "提供寵物周邊服務":"提供寵物飲水, 寵物專用餐具, 防汙墊",
    "環境服務":"提供酒精或乾洗手"
  },
  {
    "Unnamed: 0":"松山區",
    "空間數":17.0,
    "業者名稱":"舒曼六號餐館 小巨蛋南京店",
    "門市電話":"02-27188108",
    "業別":"餐飲業",
    "地址":"松山區南京東路3段303巷8弄11號1樓",
    "友善物種":"犬 (大\/中\/小型)、貓",
    "入內規定":"可落地, 需全程繫牽繩, 可不關籠,其他動物也歡迎,以不打擾其他客人為原則",
    "提供寵物周邊服務":"提供寵物飲水",
    "環境服務":"提供酒精或乾洗手"
  },
  {
    "Unnamed: 0":"松山區",
    "空間數":18.0,
    "業者名稱":"Well done cafe",
    "門市電話":"02-85228855",
    "業別":"餐飲業",
    "地址":"松山區八德路三段106巷118號",
    "友善物種":"犬 (中\/小型)、貓",
    "入內規定":"可落地, 需全程繫牽繩, 一定要著禮貌帶\/生理褲",
    "提供寵物周邊服務":"提供寵物飲水, 寵物餐, 寵物專用餐具",
    "環境服務":"協助清潔便溺物"
  },
  {
    "Unnamed: 0":"松山區",
    "空間數":19.0,
    "業者名稱":"生蠔哥海鮮燒烤",
    "門市電話":"938701210",
    "業別":"餐飲業",
    "地址":"松山區饒河街79號1樓",
    "友善物種":"犬 (小型)、貓",
    "入內規定":"可落地, 於提籠\/推車內能進入, 需全程繫牽繩, 一定要著禮貌帶\/生理褲",
    "提供寵物周邊服務":"提供寵物飲水",
    "環境服務":"提供酒精或乾洗手"
  },
  {
    "Unnamed: 0":"松山區",
    "空間數":20.0,
    "業者名稱":"좋은 날好日子咖啡",
    "門市電話":"227690609",
    "業別":"餐飲業",
    "地址":"台北市松山區延壽街129號1樓",
    "友善物種":"家犬，大型(>23公斤), 家犬，中型(9-23公斤), 家犬，小型(<9公斤), 家貓",
    "入內規定":"可落地, 需全程繫牽繩, 上椅需墊子",
    "提供寵物周邊服務":"提供寵物飲水",
    "環境服務":"提供酒精或乾洗手"
  },
  {
    "Unnamed: 0":"松山區",
    "空間數":21.0,
    "業者名稱":"松松咖啡",
    "門市電話":"0926-193-103",
    "業別":"餐飲業",
    "地址":"台北市松山區八德路四段183號1樓",
    "友善物種":"家犬，大型(>23公斤)",
    "入內規定":"無限制",
    "提供寵物周邊服務":"寵物餐",
    "環境服務":"提供酒精或乾洗手, 協助清潔便溺物, 提供狗便袋"
  },
  {
    "Unnamed: 0":"士林區",
    "空間數":1.0,
    "業者名稱":"金屋藏車食堂",
    "門市電話":"2876-0698",
    "業別":"餐飲業",
    "地址":"士林區中山北路七段140巷1號1樓",
    "友善物種":"犬 (大\/中\/小型)、貓、其它",
    "入內規定":"可落地\n 需著禮貌帶\/生理褲",
    "提供寵物周邊服務":"提供寵物餐\n  提供寵物專用餐具",
    "環境服務":"協助清潔便溺物"
  },
  {
    "Unnamed: 0":"士林區",
    "空間數":2.0,
    "業者名稱":"Brick Yard 33 1\/3 美軍俱樂部",
    "門市電話":"2861-8282",
    "業別":"餐飲業",
    "地址":"士林區凱旋路49號",
    "友善物種":"犬 (大\/中\/小型)、貓\n  其他小型動物",
    "入內規定":"室內需進提籠\/提籃\/推車\n 室外需牽繩才可落地",
    "提供寵物周邊服務":"提供寵物飲水",
    "環境服務":"提供酒精"
  },
  {
    "Unnamed: 0":"士林區",
    "空間數":3.0,
    "業者名稱":"HOLA-士林店",
    "門市電話":"2889-2000",
    "業別":"一般零售業",
    "地址":"士林區基河路258號地下1樓",
    "友善物種":"犬 (大\/中\/小型)、貓",
    "入內規定":"不可落地：需有適當防護措施(牽繩、揹袋、寵物推車或以手抱持) 需要在公司提供的推車內",
    "提供寵物周邊服務":"提供寵物推車 \n  尿布袋",
    "環境服務":"提供酒精或乾洗手\n  協助清潔便溺物\n  提供尿布墊"
  },
  {
    "Unnamed: 0":"士林區",
    "空間數":4.0,
    "業者名稱":"特力屋-士林店",
    "門市電話":"2289-1000",
    "業別":"一般零售業",
    "地址":"士林區基河路258號",
    "友善物種":"犬 (大\/中\/小型)、貓",
    "入內規定":"不可落地：需有適當防護措施(牽繩、揹袋、寵物推車或以手抱持) 需要在公司提供的推車內",
    "提供寵物周邊服務":"提供寵物推車 \n  尿布袋",
    "環境服務":"提供酒精或乾洗手"
  },
  {
    "Unnamed: 0":"士林區",
    "空間數":5.0,
    "業者名稱":"馬修單車Mathew Bike",
    "門市電話":"2832-2238",
    "業別":"一般零售業",
    "地址":"士林區文林路577號",
    "友善物種":"犬 (大\/中\/小型)、貓",
    "入內規定":"可落地",
    "提供寵物周邊服務":"提供寵物飲水",
    "環境服務":"提供酒精或乾洗手\n  提供協助清潔便溺物\n  提供狗便袋"
  },
  {
    "Unnamed: 0":"士林區",
    "空間數":6.0,
    "業者名稱":"喬治皮鞋",
    "門市電話":"2872-2288",
    "業別":"一般零售業",
    "地址":"士林區中山北路七段84號",
    "友善物種":"犬 (中\/小型)、貓",
    "入內規定":"可落地",
    "提供寵物周邊服務":"寵物牽繩掛勾",
    "環境服務":"提供酒精或乾洗手"
  },
  {
    "Unnamed: 0":"士林區",
    "空間數":7.0,
    "業者名稱":"樂活式單車館",
    "門市電話":"2885-2172",
    "業別":"一般零售業",
    "地址":"士林區承德路四段69號",
    "友善物種":"犬 (大\/中\/小型)、貓(都可以)",
    "入內規定":"可落地",
    "提供寵物周邊服務":"寵物奔跑空間",
    "環境服務":"提供酒精或乾洗手"
  },
  {
    "Unnamed: 0":"士林區",
    "空間數":8.0,
    "業者名稱":"AN58西班牙創意料理",
    "門市電話":"2885-1029",
    "業別":"餐飲業",
    "地址":"士林區承德路四段29號",
    "友善物種":"犬 (大\/中\/小型)、貓",
    "入內規定":"於提籠\/推車內才能進入",
    "提供寵物周邊服務":"提供寵物飲水",
    "環境服務":"提供酒精或乾洗手"
  },
  {
    "Unnamed: 0":"士林區",
    "空間數":9.0,
    "業者名稱":"Argent安爵銀飾工房",
    "門市電話":"02-2881-6805",
    "業別":"一般零售業",
    "地址":"士林區小北街17號",
    "友善物種":"犬 (小型)、貓",
    "入內規定":"於提籠\/推車內才能進入",
    "提供寵物周邊服務":"提供寵物飲水",
    "環境服務":"提供酒精或乾洗手"
  },
  {
    "Unnamed: 0":"士林區",
    "空間數":10.0,
    "業者名稱":"花庭園藝坊",
    "門市電話":"2810-7922",
    "業別":"一般零售業",
    "地址":"士林區延平北路七段18-2號",
    "友善物種":"犬 (大\/中\/小型)、貓、其他",
    "入內規定":"需牽繩才能落地, 勿啃咬、破壞環境",
    "提供寵物周邊服務":"園區洗手台自來水可自取",
    "環境服務":"無"
  },
  {
    "Unnamed: 0":"士林區",
    "空間數":11.0,
    "業者名稱":"君臨花坊",
    "門市電話":"2810-6011",
    "業別":"一般零售業",
    "地址":"士林區延平北路七段18-5號",
    "友善物種":"犬 (大\/中\/小型)、貓、其他",
    "入內規定":"需牽繩才能落地, 勿啃咬、破壞環境",
    "提供寵物周邊服務":"園區洗手台自來水可自取",
    "環境服務":"無"
  },
  {
    "Unnamed: 0":"士林區",
    "空間數":12.0,
    "業者名稱":"森林派對咖啡館",
    "門市電話":"2810-7709",
    "業別":"餐飲業",
    "地址":"士林區延平北路七段18-2號",
    "友善物種":"犬 (大\/中\/小型)、貓、其他",
    "入內規定":"需牽繩才能落地, 勿啃咬、破壞環境",
    "提供寵物周邊服務":"園區洗手台自來水可自取",
    "環境服務":"無"
  },
  {
    "Unnamed: 0":"士林區",
    "空間數":13.0,
    "業者名稱":"茶咖",
    "門市電話":"2813-5577",
    "業別":"餐飲業",
    "地址":"士林區社中街133號1樓",
    "友善物種":"犬 (大\/中\/小型)、貓",
    "入內規定":"可落地",
    "提供寵物周邊服務":"提供寵物飲水",
    "環境服務":"提供酒精或乾洗手,\n  協助清潔便溺物"
  },
  {
    "Unnamed: 0":"士林區",
    "空間數":14.0,
    "業者名稱":"海人選品",
    "門市電話":"8509-6779",
    "業別":"一般零售業",
    "地址":"士林區中山北路七段140巷4號1樓",
    "友善物種":"犬 (大\/中\/小型)、貓",
    "入內規定":"可落地, 於提籠\/推車內才能進入",
    "提供寵物周邊服務":"提供寵物飲水",
    "環境服務":"提供酒精或乾洗手"
  },
  {
    "Unnamed: 0":"士林區",
    "空間數":15.0,
    "業者名稱":"JB’S Diner",
    "門市電話":"2876-1588",
    "業別":"餐飲業",
    "地址":"士林區天玉街38巷16弄2號",
    "友善物種":"犬 (大\/中\/小型)、貓",
    "入內規定":"於提籠\/推車內能進入, 乘坐室外有牽繩則可落地",
    "提供寵物周邊服務":"提供寵物飲水",
    "環境服務":"提供酒精或乾洗手"
  },
  {
    "Unnamed: 0":"士林區",
    "空間數":16.0,
    "業者名稱":"創義麵 士林店",
    "門市電話":"02-2881-1078",
    "業別":"餐飲業",
    "地址":"士林區美德街32號近士林捷運站1號出口",
    "友善物種":"犬 (大\/中\/小型)、貓",
    "入內規定":"可落地, 於提籠\/推車內能進入, 需全程繫牽繩",
    "提供寵物周邊服務":"提供寵物飲水, 寵物餐",
    "環境服務":"提供酒精或乾洗手"
  },
  {
    "Unnamed: 0":"士林區",
    "空間數":17.0,
    "業者名稱":"戲咖啡",
    "門市電話":"02-2862-1999",
    "業別":"餐飲業",
    "地址":"士林區長春街12號",
    "友善物種":"犬 (大\/中\/小型)、貓",
    "入內規定":"可落地, 於提籠\/推車內能進入, 需全程繫牽繩, 一定要著禮貌帶\/生理褲",
    "提供寵物周邊服務":"提供寵物飲水, 寵物奔跑空間",
    "環境服務":"提供衛生紙"
  },
  {
    "Unnamed: 0":"士林區",
    "空間數":18.0,
    "業者名稱":"朱里昂廚房",
    "門市電話":"02-2365-3731",
    "業別":"餐飲業",
    "地址":"士林區國泰街3號",
    "友善物種":"犬 (大\/中\/小型)、貓",
    "入內規定":"可落地, 需全程繫牽繩",
    "提供寵物周邊服務":"提供寵物飲水, 寵物餐, 寵物專用餐具, 寵物奔跑空間",
    "環境服務":"提供酒精或乾洗手, 提供狗便袋"
  },
  {
    "Unnamed: 0":"士林區",
    "空間數":19.0,
    "業者名稱":"正當冰",
    "門市電話":"2891-9117",
    "業別":"餐飲業",
    "地址":"士林區前港街60號",
    "友善物種":"犬 (大\/中\/小型)、貓",
    "入內規定":"可落地，進入店家之寵物須施打預防針",
    "提供寵物周邊服務":"寵物用品販售",
    "環境服務":"提供酒精或乾洗手"
  },
  {
    "Unnamed: 0":"士林區",
    "空間數":20.0,
    "業者名稱":"金翠珠寶銀樓",
    "門市電話":"02 2831 2481",
    "業別":"珠寶業",
    "地址":"士林區中山北路六段35巷22號1樓",
    "友善物種":"犬 (大\/中\/小型)、貓",
    "入內規定":"於提籠\/推車內才能進入",
    "提供寵物周邊服務":"提供寵物飲水",
    "環境服務":"提供寵物飲水"
  },
  {
    "Unnamed: 0":"士林區",
    "空間數":21.0,
    "業者名稱":"凹屋珈琲Awoo Kohii",
    "門市電話":"0975-878-675",
    "業別":"餐飲業",
    "地址":"士林區中山北路五段505巷18號",
    "友善物種":"犬 (大\/中\/小型)、貓",
    "入內規定":"可落地",
    "提供寵物周邊服務":"提供寵物飲水",
    "環境服務":"提供酒精或乾洗手"
  },
  {
    "Unnamed: 0":"士林區",
    "空間數":22.0,
    "業者名稱":"是日好學文教機構",
    "門市電話":"0912-588-552",
    "業別":"教育業",
    "地址":"士林區忠誠路二段42號1樓",
    "友善物種":"犬 (中\/小型)、貓",
    "入內規定":"可落地, 需全程繫牽繩, 一定要著禮貌帶\/生理褲",
    "提供寵物周邊服務":"提供寵物飲水, 防汙墊",
    "環境服務":"提供酒精或乾洗手"
  },
  {
    "Unnamed: 0":"大安區",
    "空間數":1.0,
    "業者名稱":"艾斯糖咖啡",
    "門市電話":"2731-4917#20",
    "業別":"餐飲業",
    "地址":"大安區新生南路一段97巷13號",
    "友善物種":"犬 (大\/中\/小型)、貓",
    "入內規定":"可落地\n  一定要著禮貌帶\/生理褲",
    "提供寵物周邊服務":"提供寵物飲水",
    "環境服務":"提供酒精或乾洗手"
  },
  {
    "Unnamed: 0":"大安區",
    "空間數":2.0,
    "業者名稱":"全家便利商店: 和新店",
    "門市電話":"8369-1009",
    "業別":"一般零售業-便利商店",
    "地址":"大安區和平東路二段22號",
    "友善物種":"貓",
    "入內規定":"於提籠才能進入",
    "提供寵物周邊服務":"寵物用品販售",
    "環境服務":"無"
  },
  {
    "Unnamed: 0":"大安區",
    "空間數":3.0,
    "業者名稱":"阿瘦實業(股)公司: 忠孝店",
    "門市電話":"2711-8748",
    "業別":"一般零售業",
    "地址":"大安區忠孝東路四段100號1樓",
    "友善物種":"犬 (小型)",
    "入內規定":"於提籠才能進入",
    "提供寵物周邊服務":"飼主自行清潔便溺物",
    "環境服務":"提供酒精"
  },
  {
    "Unnamed: 0":"大安區",
    "空間數":4.0,
    "業者名稱":"Toast Chat",
    "門市電話":"2721-5661",
    "業別":"餐飲業",
    "地址":"大安區光復南路290巷58號1樓",
    "友善物種":"犬 (大\/中\/小型)、貓、其他",
    "入內規定":"店貓老了故暫不接待外來寵物",
    "提供寵物周邊服務":null,
    "環境服務":null
  },
  {
    "Unnamed: 0":"大安區",
    "空間數":5.0,
    "業者名稱":"Painted Nail Salon 東區美甲沙龍",
    "門市電話":"8773-9968",
    "業別":"美容業",
    "地址":"大安區延吉街138巷6號",
    "友善物種":"貓",
    "入內規定":"於提籠內才可進入\n  需有牽繩\/胸帶才可落地",
    "提供寵物周邊服務":"主人美甲時可以有寵物相伴\n  提供貓砂及食物",
    "環境服務":"提供酒精或乾洗手\n  協助清潔便溺物"
  },
  {
    "Unnamed: 0":"大安區",
    "空間數":6.0,
    "業者名稱":"貳樓Second Floor Cafe-師大店",
    "門市電話":"2365-6222",
    "業別":"餐飲業",
    "地址":"大安區師大路24號",
    "友善物種":"犬 (大\/中\/小型)、貓",
    "入內規定":"可落地",
    "提供寵物周邊服務":"免費提供寵物食用軟熟蛋",
    "環境服務":"提供酒精或乾洗手\n  協助清潔便溺物\n  桌椅消毒"
  },
  {
    "Unnamed: 0":"大安區",
    "空間數":7.0,
    "業者名稱":"貳樓Second Floor Cafe敦南店",
    "門市電話":"2700-9855",
    "業別":"餐飲業",
    "地址":"大安區敦化南路二段63巷14號",
    "友善物種":"犬 (大\/中\/小型)、貓",
    "入內規定":"可落地， 需有牽繩",
    "提供寵物周邊服務":"免費提供寵物食用軟熟蛋",
    "環境服務":"提供酒精或乾洗手\n  協助清潔便溺物\n  桌椅消毒"
  },
  {
    "Unnamed: 0":"大安區",
    "空間數":8.0,
    "業者名稱":"吐司利亞 Toasteria Café-永康店",
    "門市電話":"2321-0073",
    "業別":"餐飲業",
    "地址":"大安區信義路二段200號",
    "友善物種":"犬 (大\/中\/小型)、貓、其他",
    "入內規定":"可落地",
    "提供寵物周邊服務":"提供寵物專用餐具\n  寵物炒蛋",
    "環境服務":"提供酒精"
  },
  {
    "Unnamed: 0":"大安區",
    "空間數":9.0,
    "業者名稱":"吐司利亞Toasteria Café-敦南店",
    "門市電話":"2752-0033",
    "業別":"餐飲業",
    "地址":"大安區敦化南路一段169巷3號",
    "友善物種":"犬 (大\/中\/小型)、貓、其他",
    "入內規定":"可落地\n  提供坐墊",
    "提供寵物周邊服務":"提供寵物專用餐具\n  提供寵物炒蛋與水",
    "環境服務":"提供酒精"
  },
  {
    "Unnamed: 0":"大安區",
    "空間數":10.0,
    "業者名稱":"曜日義式餐酒館",
    "門市電話":"2708-5910",
    "業別":"餐飲業",
    "地址":"大安區東豐街53號",
    "友善物種":"犬 (大\/中\/小型)、貓、兔子、鼠類",
    "入內規定":"包廂內可落地",
    "提供寵物周邊服務":"提供寵物餐及專用餐具\n  提供奔跑空間(包廂內)",
    "環境服務":"提供協助清潔便溺物"
  },
  {
    "Unnamed: 0":"大安區",
    "空間數":11.0,
    "業者名稱":"一綠生餐飲企業有限公司\n  (The Green Room 泰式蔬食)",
    "門市電話":"2704-5208",
    "業別":"餐飲業",
    "地址":"大安區建國南路二段79巷12號",
    "友善物種":"犬 (大\/中\/小型)、貓、其他",
    "入內規定":"可落地：可以受控制即可",
    "提供寵物周邊服務":"提供寵物餐及專用餐具 \n  提供寵物飲水",
    "環境服務":"提供酒精"
  },
  {
    "Unnamed: 0":"大安區",
    "空間數":12.0,
    "業者名稱":"餵我早餐",
    "門市電話":"2700-3658",
    "業別":"餐飲業",
    "地址":"大安區建國南路二段11巷28號1樓",
    "友善物種":"犬 (大\/中\/小型)、貓",
    "入內規定":"可落地",
    "提供寵物周邊服務":"提供寵物飲水",
    "環境服務":"提供酒精或乾洗手"
  },
  {
    "Unnamed: 0":"大安區",
    "空間數":13.0,
    "業者名稱":"Woodid手作韓食",
    "門市電話":"2701-7739",
    "業別":"餐飲業",
    "地址":"大安區仁愛路四段300巷19弄6號",
    "友善物種":"犬 (大\/中\/小型)、貓\n  任何寵物",
    "入內規定":"可落地(著禮貌帶生理褲) \n  須繫牽繩\n  若有生病情況不建議進入避免交叉感染",
    "提供寵物周邊服務":"提供寵物牽繩掛勾\n  提供水與簡易寵物餐(清燙肉片)",
    "環境服務":"提供協助清潔便溺物\n  提供狗便袋"
  },
  {
    "Unnamed: 0":"大安區",
    "空間數":14.0,
    "業者名稱":"金普頓大安酒店",
    "門市電話":"2173-7999",
    "業別":"住宿業",
    "地址":"大安區仁愛路4段27巷25號",
    "友善物種":"犬 (大\/中\/小型)、貓\n  符合動物保護法規範圍內之任何動物，可進出電梯",
    "入內規定":"可落地\/牽繩\/裝籠",
    "提供寵物周邊服務":"提供寵物床墊、餐具",
    "環境服務":"提供酒精或乾洗手\n  提供狗便袋"
  },
  {
    "Unnamed: 0":"大安區",
    "空間數":15.0,
    "業者名稱":"Maryjane Pizza 瑪莉珍比薩 台大店",
    "門市電話":"2365-5222",
    "業別":"餐飲業",
    "地址":"大安區溫州街89號",
    "友善物種":"犬 (大\/中\/小型)、貓",
    "入內規定":"裝籠",
    "提供寵物周邊服務":"提供寵物專用餐具、 提供寵物水",
    "環境服務":"提供酒精或乾洗手"
  },
  {
    "Unnamed: 0":"大安區",
    "空間數":16.0,
    "業者名稱":"Maryjane Pizza 瑪莉珍比薩 師大店",
    "門市電話":"2368-5222",
    "業別":"餐飲業",
    "地址":"大安區蒲城街33-9號",
    "友善物種":"犬 (大\/中\/小型)、貓",
    "入內規定":"可落地：需著禮貌帶\/生理褲、繫牽繩",
    "提供寵物周邊服務":"提供寵物碗",
    "環境服務":"無"
  },
  {
    "Unnamed: 0":"大安區",
    "空間數":17.0,
    "業者名稱":"PORCO",
    "門市電話":"2701-5959",
    "業別":"餐飲業",
    "地址":"大安區仁愛路四段8巷31號",
    "友善物種":"犬 (大\/中\/小型)、貓",
    "入內規定":"犬可落地、貓需進籠\n  需在店外大小便完再入內\n  如已知寵物會在室內大小便，請穿禮貌帶∕生理褲\n  寵物只可待在地面或自行準備的推車內，不能上桌",
    "提供寵物周邊服務":"提供水碗",
    "環境服務":"協助清潔便溺物，視情況酌收清潔費"
  },
  {
    "Unnamed: 0":"大安區",
    "空間數":18.0,
    "業者名稱":"Plants",
    "門市電話":"2784-5677",
    "業別":"餐飲業",
    "地址":"大安區復興南路一段253巷10號",
    "友善物種":"犬 (大\/中\/小型)、貓",
    "入內規定":"可落地\n  如有攻擊性，請飼主斟酌進入",
    "提供寵物周邊服務":"提供水碗",
    "環境服務":"提供酒精或乾洗手"
  },
  {
    "Unnamed: 0":"大安區",
    "空間數":19.0,
    "業者名稱":"帕帕拉夏藝文中心",
    "門市電話":"2358-2916",
    "業別":"一般零售業",
    "地址":"大安區金華街243巷21號",
    "友善物種":"犬 (大\/中\/小型)、貓",
    "入內規定":"可落地",
    "提供寵物周邊服務":"寵物飲水",
    "環境服務":"提供酒精"
  },
  {
    "Unnamed: 0":"大安區",
    "空間數":20.0,
    "業者名稱":"become",
    "門市電話":"2700-8200",
    "業別":"餐飲業",
    "地址":"大安區信義路四段30巷50弄3號",
    "友善物種":"犬 (大\/中\/小型)、貓",
    "入內規定":"可落地，入內落地需著用尿布或禮貌帶",
    "提供寵物周邊服務":"寵物餐",
    "環境服務":"提供酒精或乾洗手"
  },
  {
    "Unnamed: 0":"大安區",
    "空間數":21.0,
    "業者名稱":"e書漫羅斯福店",
    "門市電話":"8369-1989",
    "業別":"其他",
    "地址":"大安區羅斯福路2段75號2樓",
    "友善物種":"犬 (大\/中型\/小型)小型犬要放提籠、貓",
    "入內規定":"可落地",
    "提供寵物周邊服務":"寵物專用水盆",
    "環境服務":"提供酒精或乾洗手 設有動物友善公約"
  },
  {
    "Unnamed: 0":"大安區",
    "空間數":22.0,
    "業者名稱":"益生寵愛寵物餐廳",
    "門市電話":"2708-3289",
    "業別":"餐飲業",
    "地址":"大安區和平東路二段265巷7號",
    "友善物種":"犬 (大\/中\/小型)、貓、 其他小型寵物都可以",
    "入內規定":"可落地\n  室內可用牽繩\n  需著禮貌帶\/生理褲、繫牽繩",
    "提供寵物周邊服務":"租借或販售 禮貌帶及生理褲\n  提供寵物餐\n  提供寵物專用餐具\n  提供寵物床墊、寵物用品販售\n  提供防污墊\n  提供奔跑空間、寵物柵欄",
    "環境服務":"提供酒精或乾洗手、狗便袋 協助清潔便溺物\n  室外對寵物無限制，草皮區可讓寵物培養寵際關係 設有動物友善公約"
  },
  {
    "Unnamed: 0":"大安區",
    "空間數":23.0,
    "業者名稱":"mianto 艾果豐",
    "門市電話":"2711-8473",
    "業別":"餐飲業",
    "地址":"大安區仁愛路三段123巷26弄6號",
    "友善物種":"犬 (大\/中\/小型)、兔、鳥\n  因為有工作人員貓毛過敏、如帶貓只能放戶外",
    "入內規定":"可落地\n  入內需牽繩\n  戶外有寵物柵欄，不需牽繩",
    "提供寵物周邊服務":"提供寵物專用餐具\n  戶外花園坐位區有四人座沙發，有寵物柵欄",
    "環境服務":"提供酒精或乾洗手"
  },
  {
    "Unnamed: 0":"大安區",
    "空間數":24.0,
    "業者名稱":"光一肆號",
    "門市電話":"2362-2211",
    "業別":"餐飲業",
    "地址":"大安區新生南路3段76巷2號",
    "友善物種":"犬 (大\/中\/小型)、貓",
    "入內規定":"可落地\n  於提籠\/推車\n  一定要著禮貌帶\/生理褲",
    "提供寵物周邊服務":"寵物喝水碗",
    "環境服務":"提供酒精或乾洗手"
  },
  {
    "Unnamed: 0":"大安區",
    "空間數":25.0,
    "業者名稱":"無名咖哩",
    "門市電話":"2369-1703",
    "業別":"餐飲業",
    "地址":"大安區新生南路三段68-2號",
    "友善物種":"犬 (大\/中\/小型)、貓",
    "入內規定":"可落地\n  一定要著禮貌帶\/生理褲",
    "提供寵物周邊服務":"寵物牽繩掛勾",
    "環境服務":"提供酒精或乾洗手"
  },
  {
    "Unnamed: 0":"大安區",
    "空間數":26.0,
    "業者名稱":"璞豆咖啡",
    "門市電話":"2368-9466",
    "業別":"餐飲業",
    "地址":"大安區溫州街66號",
    "友善物種":"犬 (中\/小型)、貓",
    "入內規定":"於提籠\/推車\n  一定要著禮貌帶\/生理褲",
    "提供寵物周邊服務":"狗狗飲用水",
    "環境服務":"提供酒精或乾洗手"
  },
  {
    "Unnamed: 0":"大安區",
    "空間數":27.0,
    "業者名稱":"茱莉安摩爾美語音樂美術短期補習班",
    "門市電話":"2364-5025",
    "業別":"其他",
    "地址":"大安區羅斯福路三段283巷23號1樓",
    "友善物種":"犬 (大\/中\/小型)、貓",
    "入內規定":"可落地\n  一定要著禮貌帶\/生理褲",
    "提供寵物周邊服務":"提供寵物奔跑空間\n  狗狗飲用水、零食",
    "環境服務":"提供酒精或乾洗手\n  協助清潔便溺物\n  提供狗便袋"
  },
  {
    "Unnamed: 0":"大安區",
    "空間數":28.0,
    "業者名稱":"慢步調咖啡館",
    "門市電話":"2711-2311",
    "業別":"餐飲業",
    "地址":"大安區忠孝東路三段251巷1弄1號",
    "友善物種":"犬 (大\/中\/小型)、貓",
    "入內規定":"可落地，需牽繩",
    "提供寵物周邊服務":"狗狗飲用水",
    "環境服務":"提供酒精或乾洗手\n  協助清潔便溺物\n  提供狗便袋"
  },
  {
    "Unnamed: 0":"大安區",
    "空間數":29.0,
    "業者名稱":"愛家國際蔬食餐飲",
    "門市電話":"2777-2711",
    "業別":"餐飲業",
    "地址":"大安區和平東路二段175巷7號",
    "友善物種":"犬 (大\/中\/小型)、貓",
    "入內規定":"須著禮貌帶\/生理褲才可落地",
    "提供寵物周邊服務":"提供寵物飲水, 寵物專用餐具, 寵物用品販售",
    "環境服務":"提供酒精或乾洗手"
  },
  {
    "Unnamed: 0":"大安區",
    "空間數":30.0,
    "業者名稱":"TMJ_TAIPEI",
    "門市電話":"2709-9726",
    "業別":"餐飲業",
    "地址":"台北市大安區瑞安街228號1樓",
    "友善物種":"犬 (大\/中\/小型)、貓",
    "入內規定":"可落地\n  於提籠\/推車\n  一定要著禮貌帶\/生理褲",
    "提供寵物周邊服務":"提供簡易寵物餐",
    "環境服務":"提供酒精或乾洗手"
  },
  {
    "Unnamed: 0":"大安區",
    "空間數":31.0,
    "業者名稱":"杯子裡的貓",
    "門市電話":"0976-886-926",
    "業別":"餐飲業",
    "地址":"大安區敦化南路一233巷56號",
    "友善物種":"犬 (大\/中\/小型)、貓、 其他小型寵物都可以",
    "入內規定":"於提籠\/推車內才能進入",
    "提供寵物周邊服務":"提供寵物飲水, 防汙墊",
    "環境服務":"提供酒精或乾洗手, 提供狗便袋"
  },
  {
    "Unnamed: 0":"大安區",
    "空間數":32.0,
    "業者名稱":"勺日日好空間店",
    "門市電話":"2711-0223",
    "業別":"餐飲業",
    "地址":"大安區復興南路一段206號1樓",
    "友善物種":"犬(大\/中\/小型)、貓、兔子、鳥",
    "入內規定":"可落地",
    "提供寵物周邊服務":"寵物專用餐具, 防汙墊, 寵物零食，一隻索取一份",
    "環境服務":"提供酒精或乾洗手"
  },
  {
    "Unnamed: 0":"大安區",
    "空間數":33.0,
    "業者名稱":"創義麵 忠孝店",
    "門市電話":"02-2741-1559",
    "業別":"餐飲業",
    "地址":"大安區敦化南路一段160巷62號",
    "友善物種":"犬 (大\/中\/小型)、貓",
    "入內規定":"可落地, 於提籠\/推車內能進入, 需全程繫牽繩",
    "提供寵物周邊服務":"提供寵物飲水, 寵物餐",
    "環境服務":"提供酒精或乾洗手"
  },
  {
    "Unnamed: 0":"大安區",
    "空間數":34.0,
    "業者名稱":"永憶國際有限公司",
    "門市電話":"02-27008682",
    "業別":"殯葬服務業",
    "地址":"大安區敦化南路二段1號9樓之1",
    "友善物種":"犬 (中\/小型)、貓",
    "入內規定":"可落地",
    "提供寵物周邊服務":"提供寵物飲水",
    "環境服務":"提供酒精或乾洗手, 提供狗便袋"
  },
  {
    "Unnamed: 0":"大安區",
    "空間數":35.0,
    "業者名稱":"螢火部落放感情",
    "門市電話":"02-22229998",
    "業別":"餐飲業",
    "地址":"大安區忠孝東路四段515號櫃號4",
    "友善物種":"犬 (大\/中\/小型)、貓",
    "入內規定":"可落地",
    "提供寵物周邊服務":"提供寵物飲水",
    "環境服務":"提供酒精或乾洗手"
  },
  {
    "Unnamed: 0":"大安區",
    "空間數":36.0,
    "業者名稱":"咖央咖啡館",
    "門市電話":"(02)2791-8611",
    "業別":"餐飲業",
    "地址":"大安路一段51巷2號2樓.4號2樓",
    "友善物種":"犬 (大\/中\/小型)、貓",
    "入內規定":"無限制",
    "提供寵物周邊服務":"提供寵物飲水, 寵物專用餐具, 防汙墊",
    "環境服務":"提供酒精或乾洗手"
  },
  {
    "Unnamed: 0":"大安區",
    "空間數":37.0,
    "業者名稱":"兔Dreams",
    "門市電話":"02-2703-0037",
    "業別":"餐飲業",
    "地址":"大安區新生南路一段161巷10號1樓",
    "友善物種":"犬 (大\/中\/小型)、貓",
    "入內規定":"可落地, 於提籠\/推車內能進入, 需全程繫牽繩, 兔鼠類可使用專屬放風區。如內請降低音量,毛小孩有便溺請隨手清理。",
    "提供寵物周邊服務":"提供寵物飲水, 防汙墊, 兔鼠類可使用專屬放風區。有牛肉、炒蛋、蔬果等毛小孩餐食可選購。",
    "環境服務":"提供酒精或乾洗手, 可向店員索取尿布墊。請酌量使用。"
  },
  {
    "Unnamed: 0":"大安區",
    "空間數":38.0,
    "業者名稱":"蘭亭和牛燒肉",
    "門市電話":"02-2703-0285",
    "業別":"餐飲業",
    "地址":"大安區四維路52巷12號",
    "友善物種":"犬 (大\/中\/小型)、貓",
    "入內規定":"無限制,可落地",
    "提供寵物周邊服務":"提供寵物飲水, 寵物餐, 寵物專用餐具",
    "環境服務":"提供酒精或乾洗手"
  },
  {
    "Unnamed: 0":"大安區",
    "空間數":39.0,
    "業者名稱":"牛本色 溫體牛火鍋",
    "門市電話":"02 2778 9499",
    "業別":"餐飲業",
    "地址":"大安區市民大道四段78號",
    "友善物種":"犬 (大\/中\/小型)、貓",
    "入內規定":"無限制",
    "提供寵物周邊服務":"提供寵物飲水, 寵物餐, 寵物專用餐具",
    "環境服務":"提供酒精或乾洗手, 提供狗便袋"
  },
  {
    "Unnamed: 0":"大安區",
    "空間數":40.0,
    "業者名稱":"Chao 炒炒新亞洲蔬食",
    "門市電話":"02-27753005",
    "業別":"餐飲業",
    "地址":"大安區大安路一段52巷21號1樓",
    "友善物種":"犬 (大\/中\/小型)、貓",
    "入內規定":"可落地, 於提籠\/推車內能進入, 需全程繫牽繩",
    "提供寵物周邊服務":"提供寵物飲水",
    "環境服務":"提供酒精或乾洗手"
  },
  {
    "Unnamed: 0":"大安區",
    "空間數":41.0,
    "業者名稱":"Mixigan美墨創意蔬食料理",
    "門市電話":"02-27218122",
    "業別":"餐飲業",
    "地址":"大安區延吉街137巷2號1樓",
    "友善物種":"犬 (大\/中\/小型)、貓",
    "入內規定":"可落地, 於提籠\/推車內能進入, 需全程繫牽繩",
    "提供寵物周邊服務":"提供寵物飲水",
    "環境服務":"提供酒精或乾洗手"
  },
  {
    "Unnamed: 0":"大安區",
    "空間數":42.0,
    "業者名稱":"樂子the Diner美式餐廳",
    "門市電話":"282271280",
    "業別":"餐飲業",
    "地址":"大安區瑞安街145號1F",
    "友善物種":"犬 (大\/中\/小型)、貓",
    "入內規定":"可落地, 需全程繫牽繩",
    "提供寵物周邊服務":"提供寵物飲水, 寵物餐, 寵物專用餐具, 防汙墊",
    "環境服務":"提供酒精或乾洗手"
  },
  {
    "Unnamed: 0":"大安區",
    "空間數":43.0,
    "業者名稱":"CRO#FEE 咖啡井",
    "門市電話":"無",
    "業別":"餐飲業",
    "地址":"台北市大安區忠孝東路三段248巷11-1號1樓",
    "友善物種":"家犬，大型(>23公斤), 家犬，中型(9-23公斤), 家犬，小型(<9公斤), 家貓",
    "入內規定":"可落地, 一定要著禮貌帶\/生理褲",
    "提供寵物周邊服務":"提供寵物飲水",
    "環境服務":"提供酒精或乾洗手"
  },
  {
    "Unnamed: 0":"大安區",
    "空間數":44.0,
    "業者名稱":"小南風咖啡",
    "門市電話":"223622737",
    "業別":"餐飲業",
    "地址":"台北市大安區泰順街38-1號",
    "友善物種":"家犬，大型(>23公斤), 家犬，中型(9-23公斤), 家犬，小型(<9公斤), 家貓",
    "入內規定":"可落地, 於提籠\/推車內能進入, 需全程繫牽繩",
    "提供寵物周邊服務":"提供寵物飲水",
    "環境服務":"提供酒精或乾洗手"
  },
  {
    "Unnamed: 0":"大安區",
    "空間數":45.0,
    "業者名稱":"離城放感情",
    "門市電話":"02-2222-9998",
    "業別":"餐飲業",
    "地址":"台北市大安區嘉興街345號",
    "友善物種":"家犬，大型(>23公斤), 家犬，中型(9-23公斤), 家犬，小型(<9公斤), 家貓",
    "入內規定":"無限制, 可落地",
    "提供寵物周邊服務":"提供寵物飲水",
    "環境服務":"提供酒精或乾洗手"
  },
  {
    "Unnamed: 0":"大安區",
    "空間數":46.0,
    "業者名稱":"Bonica Pâtisserie & Café",
    "門市電話":"935022207",
    "業別":"餐飲業",
    "地址":"台北市安和路二段20巷6號1樓",
    "友善物種":"家犬，大型(>23公斤), 家犬，中型(9-23公斤), 家犬，小型(<9公斤), 家貓",
    "入內規定":"無限制, 可落地",
    "提供寵物周邊服務":"提供寵物飲水, 寵物奔跑空間",
    "環境服務":"提供酒精或乾洗手, 提供狗便袋"
  },
  {
    "Unnamed: 0":"大安區",
    "空間數":47.0,
    "業者名稱":"Riff Coffee Roasters",
    "門市電話":"910370154",
    "業別":"餐飲業",
    "地址":"台北市大安區通化街39巷50弄123號",
    "友善物種":"家犬，大型(>23公斤), 家犬，中型(9-23公斤), 家犬，小型(<9公斤), 家貓",
    "入內規定":"可落地, 可以不一定要牽繩，但以不影響其他可能會介意的客人為原則",
    "提供寵物周邊服務":"提供寵物飲水",
    "環境服務":"提供酒精或乾洗手, 提供狗便袋"
  },
  {
    "Unnamed: 0":"大安區",
    "空間數":48.0,
    "業者名稱":"Space Time Bistro",
    "門市電話":"227752272",
    "業別":"餐飲業",
    "地址":"台北市大安區延吉街160巷9號1樓",
    "友善物種":"家犬，大型(>23公斤), 家犬，中型(9-23公斤), 家犬，小型(<9公斤), 家貓",
    "入內規定":"無限制, 可落地, 不負保管責任",
    "提供寵物周邊服務":"寵物用品販售",
    "環境服務":"提供酒精或乾洗手"
  },
  {
    "Unnamed: 0":"大安區",
    "空間數":49.0,
    "業者名稱":"五方食藏 忠孝",
    "門市電話":"02-27713955",
    "業別":"餐飲業",
    "地址":"台北市大安區忠孝東路四段170巷17弄5號",
    "友善物種":"家犬，大型(>23公斤), 家犬，中型(9-23公斤), 家犬，小型(<9公斤), 家貓",
    "入內規定":"需全程繫牽繩, 依據門市空間各有限制且需訂位前告知 ; 忠孝門市 需牽繩有特別友善區域",
    "提供寵物周邊服務":"提供寵物飲水",
    "環境服務":"提供酒精或乾洗手"
  },
  {
    "Unnamed: 0":"大安區",
    "空間數":50.0,
    "業者名稱":"五方食藏 青田",
    "門市電話":"02-2395-9388",
    "業別":"餐飲業",
    "地址":"台北市大安區青田街6巷15號",
    "友善物種":"家犬，大型(>23公斤), 家犬，中型(9-23公斤), 家犬，小型(<9公斤), 家貓",
    "入內規定":"於提籠\/推車內能進入, 需全程繫牽繩, 青田門市 室內僅限小型犬需提籠 ,戶外區域 需牽繩",
    "提供寵物周邊服務":"提供寵物飲水",
    "環境服務":"提供酒精或乾洗手"
  },
  {
    "Unnamed: 0":"大同區",
    "空間數":1.0,
    "業者名稱":"兜味咖啡",
    "門市電話":"2557-3169",
    "業別":"餐飲業",
    "地址":"大同區安西街36號",
    "友善物種":"犬(中\/小型)、貓",
    "入內規定":"可落地, 一定要著禮貌帶\/生理褲",
    "提供寵物周邊服務":"販售禮貌帶及生理褲, 提供寵物餐, 提供寵物專用餐具, 提供寵物牽繩勾",
    "環境服務":"提供酒精或乾洗手, 提供狗便袋"
  },
  {
    "Unnamed: 0":"大同區",
    "空間數":2.0,
    "業者名稱":"大華行竹木造咖",
    "門市電話":"2553-0482",
    "業別":"一般零售業",
    "地址":"大同區迪化街一段161號",
    "友善物種":"犬 (大\/中\/小型)、貓",
    "入內規定":"可落地",
    "提供寵物周邊服務":"提供寵物飲水",
    "環境服務":"提供酒精或乾洗手、設有動物友善公約"
  },
  {
    "Unnamed: 0":"大同區",
    "空間數":3.0,
    "業者名稱":"樂芙莉Lovely",
    "門市電話":"2553-9883",
    "業別":"一般零售業",
    "地址":"大同區迪化街一段186號",
    "友善物種":"犬 (大\/中\/小型)、貓\n  小型動物",
    "入內規定":"可落地, 一定要著禮貌帶／生理褲",
    "提供寵物周邊服務":"提供寵物飲水",
    "環境服務":"提供酒精或乾洗手, 提供寵物飲水"
  },
  {
    "Unnamed: 0":"大同區",
    "空間數":4.0,
    "業者名稱":"永利百崧食品-五色本物",
    "門市電話":"2553-2438",
    "業別":"一般零售業",
    "地址":"大同區迪化街一段143號",
    "友善物種":"犬 (大\/中\/小型)、貓",
    "入內規定":"可落地",
    "提供寵物周邊服務":"寵物可自行遊走",
    "環境服務":"提供酒精或乾洗手"
  },
  {
    "Unnamed: 0":"大同區",
    "空間數":5.0,
    "業者名稱":"元氣毛孩",
    "門市電話":"0970-841-447",
    "業別":"一般零售業",
    "地址":"大同區迪化街一段14巷2號",
    "友善物種":"犬 (大\/中\/小型)、貓",
    "入內規定":"可落地",
    "提供寵物周邊服務":"寵物可於1樓店內空間活動, 提供寵物飲水",
    "環境服務":"提供酒精或乾洗手, 提供狗便袋"
  },
  {
    "Unnamed: 0":"大同區",
    "空間數":6.0,
    "業者名稱":"Her Rose",
    "門市電話":"2559-4033",
    "業別":"餐飲業",
    "地址":"大同區赤峰街53巷21號",
    "友善物種":"犬 (大\/中\/小型)、貓",
    "入內規定":"可落地, 一定要著禮貌帶／生理褲",
    "提供寵物周邊服務":"販售 禮貌帶及生理褲, 提供寵物餐, 提供寵物專用餐具, 提供寵物飲水器及寵物玩具",
    "環境服務":"提供酒精或乾洗手、狗便袋 協助清潔便溺物\n  設有動物友善公約"
  },
  {
    "Unnamed: 0":"大同區",
    "空間數":7.0,
    "業者名稱":"21工房",
    "門市電話":"2585-1913",
    "業別":"餐飲業",
    "地址":"大同區酒泉街10巷25號",
    "友善物種":"犬(小型)",
    "入內規定":"於提籠\/推車內才能進入",
    "提供寵物周邊服務":"提供寵物飲水",
    "環境服務":"提供酒精或乾洗手"
  },
  {
    "Unnamed: 0":"大同區",
    "空間數":8.0,
    "業者名稱":"浮光書店",
    "門市電話":"2550-7288",
    "業別":"其他-複合式書店",
    "地址":"大同區赤峰街47巷16號2樓",
    "友善物種":"犬 (中\/小型)、貓",
    "入內規定":"可落地",
    "提供寵物周邊服務":"提供寵物飲水",
    "環境服務":"提供酒精或乾洗手"
  },
  {
    "Unnamed: 0":"大同區",
    "空間數":9.0,
    "業者名稱":"六安堂參藥行",
    "門市電話":"2559-8599",
    "業別":"一般零售業",
    "地址":"大同區迪化街一段75號",
    "友善物種":"犬 (大\/中\/小型)、貓",
    "入內規定":"需牽繩才可落地或於提籠\/推車內才能進入",
    "提供寵物周邊服務":"提供寵物飲水",
    "環境服務":"提供酒精或乾洗手"
  },
  {
    "Unnamed: 0":"大同區",
    "空間數":10.0,
    "業者名稱":"阿立圓山玩具模型社",
    "門市電話":"2585-9491",
    "業別":"一般零售業",
    "地址":"大同區酒泉街31號1樓",
    "友善物種":"犬(大\/中\/小型)、 家貓",
    "入內規定":"寵物可落地",
    "提供寵物周邊服務":"提供寵物飲水",
    "環境服務":"提供酒精或乾洗手"
  },
  {
    "Unnamed: 0":"大同區",
    "空間數":11.0,
    "業者名稱":"漫花時",
    "門市電話":"2556-0545",
    "業別":"一般零售業",
    "地址":"大同區迪化街一段8號",
    "友善物種":"犬(大\/中\/小型)、 家貓",
    "入內規定":"可落地, 於提籠\/推車內才能進入",
    "提供寵物周邊服務":"提供寵物飲水",
    "環境服務":"提供酒精或乾洗手"
  },
  {
    "Unnamed: 0":"大同區",
    "空間數":12.0,
    "業者名稱":"旭牧高纖沙拉輕食-酒泉店",
    "門市電話":"02 2596 0618",
    "業別":"餐飲業",
    "地址":"大同區酒泉街76號",
    "友善物種":"犬 (大型)",
    "入內規定":"可落地",
    "提供寵物周邊服務":"提供寵物飲水, 寵物餐",
    "環境服務":"提供酒精或乾洗手, 協助清潔便溺物"
  },
  {
    "Unnamed: 0":"大同區",
    "空間數":13.0,
    "業者名稱":"沐沐家",
    "門市電話":null,
    "業別":"餐飲業",
    "地址":"大同區雙連街51號1樓",
    "友善物種":"犬 (大\/中\/小型)、貓、其他",
    "入內規定":"可落地",
    "提供寵物周邊服務":"提供寵物飲水, 寵物奔跑空間",
    "環境服務":"提供酒精或乾洗手"
  },
  {
    "Unnamed: 0":"大同區",
    "空間數":14.0,
    "業者名稱":"小珊食堂",
    "門市電話":"02-25560877",
    "業別":"餐飲業",
    "地址":"台北市大同區赤峰街79號",
    "友善物種":"犬 (中\/小型)",
    "入內規定":"可落地",
    "提供寵物周邊服務":"提供寵物飲水, 寵物牽繩掛勾",
    "環境服務":"提供酒精或乾洗手, 提供狗便袋"
  },
  {
    "Unnamed: 0":"大同區",
    "空間數":15.0,
    "業者名稱":"鼠皮咖啡 soopi cafe",
    "門市電話":"0909-679-709",
    "業別":"餐飲業",
    "地址":"大同區延平北路二段61巷22號1樓",
    "友善物種":"犬 (大\/中\/小型)、貓、其他",
    "入內規定":"可落地, 需全程繫牽繩, 飼主自行斟酌是否需要穿上禮貌帶，因寵物在店內便溺會收取清潔費500元。",
    "提供寵物周邊服務":"提供寵物飲水, 寵物餐",
    "環境服務":"提供酒精或乾洗手"
  },
  {
    "Unnamed: 0":"大同區",
    "空間數":16.0,
    "業者名稱":"翔仔居家-台北中山店",
    "門市電話":"225211381",
    "業別":"一般零售業",
    "地址":"大同區赤峰街41巷8號一樓",
    "友善物種":"犬 (大\/中\/小型)、貓",
    "入內規定":"無限制",
    "提供寵物周邊服務":"販售毛巾、涼感墊...等相關配件商品",
    "環境服務":"提供酒精或乾洗手, 協助清潔便溺物"
  },
  {
    "Unnamed: 0":"大同區",
    "空間數":17.0,
    "業者名稱":"桔物手作",
    "門市電話":"933159071",
    "業別":"一般零售業",
    "地址":"大同區民生西路362巷23號3樓",
    "友善物種":"犬 (大\/中\/小型)、貓",
    "入內規定":"無限制",
    "提供寵物周邊服務":"提供寵物飲水",
    "環境服務":"提供狗便袋"
  },
  {
    "Unnamed: 0":"大同區",
    "空間數":18.0,
    "業者名稱":"Modern Mode Café",
    "門市電話":"（02）25571083",
    "業別":"餐飲業",
    "地址":"台北市迪化街一段278號",
    "友善物種":"家犬，大型(>23公斤), 家犬，中型(9-23公斤), 家犬，小型(<9公斤), 家貓",
    "入內規定":"可落地, 需確認店內用餐客人無貓狗嚴重過敏者",
    "提供寵物周邊服務":"提供寵物飲水",
    "環境服務":"提供酒精或乾洗手"
  },
  {
    "Unnamed: 0":"大同區",
    "空間數":19.0,
    "業者名稱":"Vis cafe深夜咖啡",
    "門市電話":"225862321",
    "業別":"餐飲業",
    "地址":"台北市大同區酒泉街34-3號",
    "友善物種":"家犬，大型(>23公斤), 家犬，中型(9-23公斤), 家犬，小型(<9公斤), 家貓",
    "入內規定":"無限制, 只要不影響其他客人",
    "提供寵物周邊服務":"提供寵物飲水",
    "環境服務":"自備"
  },
  {
    "Unnamed: 0":"大同區",
    "空間數":20.0,
    "業者名稱":"水羿云飛",
    "門市電話":"988751842",
    "業別":"餐飲業",
    "地址":"台北市大同區寧夏路34號",
    "友善物種":"家犬，大型(>23公斤), 家犬，中型(9-23公斤), 家犬，小型(<9公斤), 家貓",
    "入內規定":"可落地, 需全程繫牽繩",
    "提供寵物周邊服務":"提供寵物飲水, 寵物牽繩掛勾",
    "環境服務":"提供酒精或乾洗手"
  },
  {
    "Unnamed: 0":"大同區",
    "空間數":21.0,
    "業者名稱":"五方食藏 大稻埕",
    "門市電話":"02-25508239",
    "業別":"餐飲業",
    "地址":"台北市大同區迪化街一段202號",
    "友善物種":"家犬，大型(>23公斤), 家犬，中型(9-23公斤), 家犬，小型(<9公斤), 家貓",
    "入內規定":"需全程繫牽繩, 大稻埕 需牽繩",
    "提供寵物周邊服務":"提供寵物飲水",
    "環境服務":"提供酒精或乾洗手"
  },
  {
    "Unnamed: 0":"萬華區",
    "空間數":1.0,
    "業者名稱":"全家便利商店 :日祥店",
    "門市電話":"2333-1039",
    "業別":"一般零售業-便利商店",
    "地址":"萬華區青年路154號",
    "友善物種":"犬 (大\/中\/小型)、貓",
    "入內規定":"無限制",
    "提供寵物周邊服務":"寵物用品販售",
    "環境服務":"提供狗便袋"
  },
  {
    "Unnamed: 0":"萬華區",
    "空間數":2.0,
    "業者名稱":"AK12美式小館",
    "門市電話":"2361-0136",
    "業別":"餐飲業",
    "地址":"萬華區峨嵋街12號2樓",
    "友善物種":"犬 (大\/中\/小型)、貓",
    "入內規定":"可落地(寵物店內都會提供椅子，不建議落地，除了大型犬)\n  需著禮貌帶\/生理褲\n  需繩子、提籠",
    "提供寵物周邊服務":"提供寵物餐及專用餐具\n  提供小型寵物椅子",
    "環境服務":"提供酒精\n  提供協助清潔便溺物\n  提供狗便袋"
  },
  {
    "Unnamed: 0":"萬華區",
    "空間數":3.0,
    "業者名稱":"麗紅人文茶館",
    "門市電話":"2388-3528(空號)",
    "業別":"餐飲業",
    "地址":"萬華區武昌街二段116-1號",
    "友善物種":"犬 (大\/中\/小型)、貓",
    "入內規定":"可落地",
    "提供寵物周邊服務":"提供寵物飲水",
    "環境服務":"提供狗便袋"
  },
  {
    "Unnamed: 0":"萬華區",
    "空間數":4.0,
    "業者名稱":"水晶玫瑰有限公司 \n  (Crystal Rose Ribbon 緞帶專賣)",
    "門市電話":"2302-3968",
    "業別":"一般零售業",
    "地址":"萬華區艋舺大道188號",
    "友善物種":"犬 (大\/中\/小型)、貓、其他",
    "入內規定":"可落地",
    "提供寵物周邊服務":"提供寵物飲水",
    "環境服務":"提供協助清潔便溺物"
  },
  {
    "Unnamed: 0":"萬華區",
    "空間數":5.0,
    "業者名稱":"富樂市-敦仁餐飲有限公司",
    "門市電話":"2311-0008",
    "業別":"餐飲業",
    "地址":"萬華區貴陽街二段7號",
    "友善物種":"犬 (大\/中\/小型)、貓",
    "入內規定":"可落地",
    "提供寵物周邊服務":"提供寵物飲水",
    "環境服務":"提供酒精或乾洗手、協助清潔便溺物"
  },
  {
    "Unnamed: 0":"萬華區",
    "空間數":6.0,
    "業者名稱":"金輪轉甜水堂",
    "門市電話":"2389-6934",
    "業別":"餐飲業",
    "地址":"萬華區昆明街230號1樓",
    "友善物種":"犬 (大\/中\/小型)、貓",
    "入內規定":"可落地，需要牽繩",
    "提供寵物周邊服務":"提供寵物飲水",
    "環境服務":"提供酒精或乾洗手"
  },
  {
    "Unnamed: 0":"萬華區",
    "空間數":7.0,
    "業者名稱":"Mr. Voice 陳威宇歌唱教學系統",
    "門市電話":"2304-1588",
    "業別":"其他-教育類",
    "地址":"萬華區艋舺大道128號1樓",
    "友善物種":"犬 (中\/小型)、貓",
    "入內規定":"可落地",
    "提供寵物周邊服務":"無",
    "環境服務":"提供酒精或乾洗手"
  },
  {
    "Unnamed: 0":"萬華區",
    "空間數":8.0,
    "業者名稱":"本願豆花店",
    "門市電話":"0988-576-776",
    "業別":"餐飲業",
    "地址":"萬華區貴陽街二段1號",
    "友善物種":"犬 (大\/中\/小型)",
    "入內規定":"可落地",
    "提供寵物周邊服務":"提供寵物奔跑空間",
    "環境服務":"提供酒精或乾洗手\n  提供狗便袋"
  },
  {
    "Unnamed: 0":"萬華區",
    "空間數":9.0,
    "業者名稱":"瑞格華有限公司\/大海刀品",
    "門市電話":"2312-0816",
    "業別":"一般零售業",
    "地址":"西寧南路101號",
    "友善物種":"犬 (小型)、 貓",
    "入內規定":"可落地",
    "提供寵物周邊服務":"無",
    "環境服務":"提供酒精或乾洗手"
  },
  {
    "Unnamed: 0":"萬華區",
    "空間數":10.0,
    "業者名稱":"抱瓶庵藝事空間",
    "門市電話":"2388-5218",
    "業別":"其他-文創業",
    "地址":"萬華區開封街二段62-5號",
    "友善物種":"犬 (大\/中\/小型)、貓",
    "入內規定":"可落地",
    "提供寵物周邊服務":"提供寵物飲水",
    "環境服務":"提供酒精或乾洗手\n  協助清潔便溺物\n  提供狗便袋"
  },
  {
    "Unnamed: 0":"萬華區",
    "空間數":11.0,
    "業者名稱":"兩喜號 Liang Xi Hao - 總店",
    "門市電話":"2336-6887",
    "業別":"餐飲業",
    "地址":"萬華區廣州街245號",
    "友善物種":"犬 (大\/中\/小型)、貓",
    "入內規定":"可落地",
    "提供寵物周邊服務":"提供寵物飲水",
    "環境服務":"提供酒精或乾洗手"
  },
  {
    "Unnamed: 0":"萬華區",
    "空間數":12.0,
    "業者名稱":"兩喜號 Liang Xi Hao - 西園店",
    "門市電話":"2336-1129",
    "業別":"餐飲業",
    "地址":"萬華區西園路一段194號",
    "友善物種":"犬 (大\/中\/小型)、貓",
    "入內規定":"可落地",
    "提供寵物周邊服務":"提供寵物飲水",
    "環境服務":"提供酒精或乾洗手"
  },
  {
    "Unnamed: 0":"萬華區",
    "空間數":13.0,
    "業者名稱":"小王煮瓜",
    "門市電話":"2370-7118",
    "業別":"餐飲業",
    "地址":"萬華區華西街17之4號",
    "友善物種":"犬 (大\/中\/小型)、貓",
    "入內規定":"可落地",
    "提供寵物周邊服務":"提供寵物飲水",
    "環境服務":"提供酒精或乾洗手"
  },
  {
    "Unnamed: 0":"萬華區",
    "空間數":14.0,
    "業者名稱":"冠婷服飾行",
    "門市電話":"2308-0703",
    "業別":"服飾業",
    "地址":"萬華區康定路239，241號1樓",
    "友善物種":"犬 (大\/中\/小型)、貓",
    "入內規定":"可落地",
    "提供寵物周邊服務":"提供寵物飲水",
    "環境服務":"提供酒精或乾洗手"
  },
  {
    "Unnamed: 0":"萬華區",
    "空間數":15.0,
    "業者名稱":"THE garden",
    "門市電話":"2311-0587",
    "業別":"餐飲業",
    "地址":"萬華區成都路10巷31、33號1樓",
    "友善物種":"犬 (大\/中\/小型)、貓",
    "入內規定":"可落地",
    "提供寵物周邊服務":"提供寵物飲水",
    "環境服務":"提供酒精或乾洗手, 提供狗便袋"
  },
  {
    "Unnamed: 0":"萬華區",
    "空間數":16.0,
    "業者名稱":"喜舍居酒屋",
    "門市電話":"2332-1868",
    "業別":"餐飲業",
    "地址":"萬華區東園街68-1號",
    "友善物種":"犬 (大\/中\/小型)、貓",
    "入內規定":"可落地",
    "提供寵物周邊服務":"提供寵物飲水",
    "環境服務":"提供酒精或乾洗手"
  },
  {
    "Unnamed: 0":"萬華區",
    "空間數":17.0,
    "業者名稱":"Haooyun Station 好運站",
    "門市電話":"0981-345-930",
    "業別":"餐飲業",
    "地址":"中華路二段416巷88號",
    "友善物種":"犬（小型）",
    "入內規定":"可落地",
    "提供寵物周邊服務":"提供寵物飲水\n  寵物餐\n  寵物專用餐具",
    "環境服務":"提供酒精或乾洗手"
  },
  {
    "Unnamed: 0":"萬華區",
    "空間數":18.0,
    "業者名稱":"樂野食",
    "門市電話":"02-2388-8088",
    "業別":"餐飲業",
    "地址":"萬華區武昌街二段37號5樓",
    "友善物種":"犬 (中\/小型)、貓",
    "入內規定":"可落地, 不會影響到其他客人即可",
    "提供寵物周邊服務":"可落地, 不會影響到其他客人即可",
    "環境服務":"提供寵物飲水, 寵物餐"
  },
  {
    "Unnamed: 0":"萬華區",
    "空間數":19.0,
    "業者名稱":"思沐咖啡",
    "門市電話":"02-23036787",
    "業別":"餐飲業",
    "地址":"萬華西園路二段281巷27號",
    "友善物種":"犬 (大\/中\/小型)、貓、其他",
    "入內規定":"於提籠\/推車才能進入",
    "提供寵物周邊服務":"提供寵物飲水",
    "環境服務":"提供酒精或乾洗手, 協助清潔便溺物, 提供狗便袋"
  },
  {
    "Unnamed: 0":"萬華區",
    "空間數":20.0,
    "業者名稱":"Bear Junkies熊飲(早\n  午餐&酒吧)",
    "門市電話":"02-23118525",
    "業別":"餐飲業",
    "地址":"萬華區昆明街192號2樓",
    "友善物種":"犬 (中\/小型)、貓",
    "入內規定":"可落地 一定要著禮貌帶、生理褲",
    "提供寵物周邊服務":"提供寵物飲水, 寵物餐、寵物專用餐具",
    "環境服務":"提供酒精或乾洗手, 協助清潔便溺物, 提供狗便袋"
  },
  {
    "Unnamed: 0":"萬華區",
    "空間數":21.0,
    "業者名稱":"木咖",
    "門市電話":"0986-872-404",
    "業別":"餐飲業",
    "地址":"萬華區貴陽街二段40巷6號",
    "友善物種":"犬 (大\/中\/小型)、貓",
    "入內規定":"無限制",
    "提供寵物周邊服務":"寵物奔跑空間",
    "環境服務":"提供酒精或乾洗手"
  },
  {
    "Unnamed: 0":"萬華區",
    "空間數":22.0,
    "業者名稱":"AL REVÉS 顛倒餐廳",
    "門市電話":"02-2375-1221",
    "業別":"餐飲業",
    "地址":"萬華區昆明街131號",
    "友善物種":"犬(大\/中\/小型)、貓",
    "入內規定":"可落地要有牽繩",
    "提供寵物周邊服務":null,
    "環境服務":null
  },
  {
    "Unnamed: 0":"萬華區",
    "空間數":23.0,
    "業者名稱":"奔FUN足體工坊",
    "門市電話":"2331-1067",
    "業別":"美容業",
    "地址":"萬華區武昌街二段85-4號",
    "友善物種":"犬 (大\/中\/小型)、貓",
    "入內規定":"可落地, 於提籠\/推車內能進入, 一定要著禮貌帶\/生理褲",
    "提供寵物周邊服務":"提供寵物飲水",
    "環境服務":"提供酒精或乾洗手, 協助清潔便溺物"
  },
  {
    "Unnamed: 0":"萬華區",
    "空間數":24.0,
    "業者名稱":"心丰御膳",
    "門市電話":"0979-769-722",
    "業別":"餐飲業",
    "地址":"萬華區長泰街139巷二之一號",
    "友善物種":"家犬，大型(>23公斤), 家犬，中型(9-23公斤), 家犬，小型(<9公斤), 家貓",
    "入內規定":"可落地, 一定要著禮貌帶\/生理褲",
    "提供寵物周邊服務":"提供寵物飲水, 寵物餐, 寵物專用餐具, 寵物奔跑空間",
    "環境服務":"提供酒精或乾洗手, 協助清潔便溺物, 提供狗便袋"
  },
  {
    "Unnamed: 0":"萬華區",
    "空間數":25.0,
    "業者名稱":"家香味食堂",
    "門市電話":"02-23099285",
    "業別":"餐飲業",
    "地址":"萬華區長泰街7號",
    "友善物種":"家犬，中型(9-23公斤), 家犬，小型(<9公斤), 家貓",
    "入內規定":"無限制",
    "提供寵物周邊服務":"提供寵物飲水",
    "環境服務":"提供酒精或乾洗手"
  },
  {
    "Unnamed: 0":"萬華區",
    "空間數":26.0,
    "業者名稱":"本願豆花店-漢中",
    "門市電話":"0905-311-290",
    "業別":"餐飲業",
    "地址":"萬華區漢中街32巷1號",
    "友善物種":"犬(大\/中\/小型)、貓",
    "入內規定":"可落地, 於提籠\/推車內能進入",
    "提供寵物周邊服務":"提供寵物飲水",
    "環境服務":"提供酒精或乾洗手"
  },
  {
    "Unnamed: 0":"萬華區",
    "空間數":27.0,
    "業者名稱":"小鍋巴",
    "門市電話":"02-23393025",
    "業別":"餐飲業",
    "地址":"萬華區國興路6號",
    "友善物種":"犬(大\/中型)、貓",
    "入內規定":"不影響其他客人用餐",
    "提供寵物周邊服務":"提供寵物飲水",
    "環境服務":"提供酒精或乾洗手"
  },
  {
    "Unnamed: 0":"中正區",
    "空間數":1.0,
    "業者名稱":"全家便利商店: 文祥店",
    "門市電話":"2391-4884",
    "業別":"一般零售業-便利商店",
    "地址":"中正區杭州南路一段147號",
    "友善物種":"犬 (大\/中\/小型)、貓",
    "入內規定":"於提籠才能進入",
    "提供寵物周邊服務":"寵物用品販售",
    "環境服務":"無"
  },
  {
    "Unnamed: 0":"中正區",
    "空間數":2.0,
    "業者名稱":"兒莫造型名店 A'mour Hair Salon",
    "門市電話":"2368-6788",
    "業別":"美容業",
    "地址":"中正區汀州路三段146號2樓",
    "友善物種":"犬 (小型)、 貓",
    "入內規定":"要牽繩才可落地",
    "提供寵物周邊服務":"無",
    "環境服務":"無"
  },
  {
    "Unnamed: 0":"中正區",
    "空間數":3.0,
    "業者名稱":"貳樓Second Floor Cafe微風店",
    "門市電話":"2361-0861",
    "業別":"餐飲業",
    "地址":"中正區北平西路3號(台北車站2樓)",
    "友善物種":"犬 (大\/中\/小型)、貓",
    "入內規定":"可落地",
    "提供寵物周邊服務":"免費提供寵物食用軟熟蛋",
    "環境服務":"提供酒精"
  },
  {
    "Unnamed: 0":"中正區",
    "空間數":4.0,
    "業者名稱":"貳樓Second Floor Cafe公館店",
    "門市電話":"2364-1666",
    "業別":"餐飲業",
    "地址":"中正區羅斯福路三段316巷9弄7號",
    "友善物種":"犬 (大\/中\/小型)、貓",
    "入內規定":"可落地",
    "提供寵物周邊服務":"免費提供寵物食用軟熟蛋",
    "環境服務":"無"
  },
  {
    "Unnamed: 0":"中正區",
    "空間數":5.0,
    "業者名稱":"Mr.雪腐-公館店",
    "門市電話":"2363-5200",
    "業別":"餐飲業",
    "地址":"中正區羅斯福路三段244巷21號",
    "友善物種":"犬 (大\/中\/小型)、貓\n  其他：會動的都行",
    "入內規定":"可落地",
    "提供寵物周邊服務":"提供寵物飲用水",
    "環境服務":"提供酒精或乾洗手"
  },
  {
    "Unnamed: 0":"中正區",
    "空間數":6.0,
    "業者名稱":"快樂數位影像器材有限公司",
    "門市電話":"2331-0554\/2331-1488",
    "業別":"一般零售業",
    "地址":"中正區漢口街一段73-1號1樓",
    "友善物種":"犬 (大\/中\/小型)、貓",
    "入內規定":"可落地",
    "提供寵物周邊服務":"提供寵物飲水",
    "環境服務":"提供協助清潔便溺物\/酒精或乾洗手"
  },
  {
    "Unnamed: 0":"中正區",
    "空間數":7.0,
    "業者名稱":"沐樂咖啡-新生店",
    "門市電話":"2358-7288",
    "業別":"餐飲業",
    "地址":"中正區臨沂街13巷7號",
    "友善物種":"犬 (大\/中\/小型)",
    "入內規定":"可落地",
    "提供寵物周邊服務":"提供寵物飲水",
    "環境服務":"提供酒精"
  },
  {
    "Unnamed: 0":"中正區",
    "空間數":8.0,
    "業者名稱":"OOH CHA CHA自然食",
    "門市電話":"2367-7133",
    "業別":"餐飲業",
    "地址":"中正區南昌路二段207號1樓",
    "友善物種":"犬 (大\/中\/小型)、貓、其他",
    "入內規定":"於提籠才能進入",
    "提供寵物周邊服務":"提供寵物飲水",
    "環境服務":"提供酒精、 協助清潔便溺物"
  },
  {
    "Unnamed: 0":"中正區",
    "空間數":9.0,
    "業者名稱":"市長官邸藝文沙龍",
    "門市電話":"2396-8198",
    "業別":"其他",
    "地址":"中正區徐州路46號",
    "友善物種":"犬 (中\/小型)",
    "入內規定":"可落地、室內區域不可落地\n  前庭廣場、後院廣場 表演方可讓寵物落地進場，餐廳及歷史建物區則不可入內",
    "提供寵物周邊服務":"寵物奔跑空間",
    "環境服務":"提供酒精或乾洗手\n  協助清潔便溺物\n  提供狗便袋"
  },
  {
    "Unnamed: 0":"中正區",
    "空間數":10.0,
    "業者名稱":"貳樓Second Floor Café-仁愛店",
    "門市電話":"02 2357 9222",
    "業別":"餐飲業",
    "地址":"中正區仁愛路二段108號",
    "友善物種":"犬 (大\/中\/小型)、貓",
    "入內規定":"可落地",
    "提供寵物周邊服務":"免費提供寵物食用軟熟蛋",
    "環境服務":"無"
  },
  {
    "Unnamed: 0":"中正區",
    "空間數":11.0,
    "業者名稱":"成功攝影",
    "門市電話":"2351-8918",
    "業別":"一般零售業",
    "地址":"中正區臨沂街3巷31號",
    "友善物種":"犬 (中\/小型)、貓",
    "入內規定":"可落地",
    "提供寵物周邊服務":"無",
    "環境服務":"提供酒精或乾洗手"
  },
  {
    "Unnamed: 0":"中正區",
    "空間數":12.0,
    "業者名稱":"林屋照相器材有限公司",
    "門市電話":"2311-8796",
    "業別":"一般零售業",
    "地址":"中正區開封街一段71號",
    "友善物種":"犬 (大\/中\/小型)、貓",
    "入內規定":"可落地",
    "提供寵物周邊服務":"無",
    "環境服務":"提供酒精或乾洗手"
  },
  {
    "Unnamed: 0":"中正區",
    "空間數":13.0,
    "業者名稱":"Easy Coffee",
    "門市電話":"2395-6102",
    "業別":"餐飲業",
    "地址":"中正區忠孝東路一段58號B1",
    "友善物種":"犬 (小型)、貓",
    "入內規定":"可落地",
    "提供寵物周邊服務":"提供寵物飲水",
    "環境服務":"提供酒精或乾洗手"
  },
  {
    "Unnamed: 0":"中正區",
    "空間數":14.0,
    "業者名稱":"地下街軟體世界2號店",
    "門市電話":"2556-7531",
    "業別":"一般零售業",
    "地址":"中正區市民大道1段100號B1電子三區76號",
    "友善物種":"犬 (小型)、貓",
    "入內規定":"於提籠\/推車內才能進入",
    "提供寵物周邊服務":"提供寵物飲水",
    "環境服務":"提供酒精或乾洗手"
  },
  {
    "Unnamed: 0":"中正區",
    "空間數":15.0,
    "業者名稱":"艾葳精品婚紗",
    "門市電話":"2356-0388",
    "業別":"其他-婚紗業",
    "地址":"中正區愛國東路42號",
    "友善物種":"犬 (大\/中\/小型)、貓",
    "入內規定":"可落地",
    "提供寵物周邊服務":"提供寵物飲水,\n  提供寵物參與攝影",
    "環境服務":"提供酒精或乾洗手"
  },
  {
    "Unnamed: 0":"中正區",
    "空間數":16.0,
    "業者名稱":"路境行旅",
    "門市電話":"2389-9595",
    "業別":"住宿業",
    "地址":"中正區重慶南路一段86號B1",
    "友善物種":"犬 (小型)、貓",
    "入內規定":"於提籠\/推車內才能進入",
    "提供寵物周邊服務":"提供寵物奔跑空間、相關備品、寵物專用餐具",
    "環境服務":"提供酒精或乾洗手"
  },
  {
    "Unnamed: 0":"中正區",
    "空間數":17.0,
    "業者名稱":"啼岸 Vegan Resort",
    "門市電話":"2368-2913",
    "業別":"餐飲業",
    "地址":"中正區牯嶺街133號",
    "友善物種":"犬 (大\/中\/小型)、貓、其他",
    "入內規定":"可落地(須留在身邊)",
    "提供寵物周邊服務":"提供寵物飲水",
    "環境服務":"提供酒精或乾洗手"
  },
  {
    "Unnamed: 0":"中正區",
    "空間數":18.0,
    "業者名稱":"Labu cafe",
    "門市電話":"2351-6210",
    "業別":"餐飲業",
    "地址":"中正區信義路二段161巷2弄7號",
    "友善物種":"犬 (中\/小型)、貓",
    "入內規定":"可落地, 一定要著禮貌帶\/生理褲, 不影響其他人用餐為主",
    "提供寵物周邊服務":"提供寵物飲水",
    "環境服務":"提供酒精或乾洗手"
  },
  {
    "Unnamed: 0":"中正區",
    "空間數":19.0,
    "業者名稱":"稻邸",
    "門市電話":"0970-215-093",
    "業別":"餐飲業",
    "地址":"迪化街一段299號",
    "友善物種":"犬 (大\/中\/小型)、貓",
    "入內規定":"可落地\n  一定要著禮貌帶／生理褲",
    "提供寵物周邊服務":"販售 禮貌帶及生理褲\n  提供寵物餐\n  提供寵物專用餐具",
    "環境服務":"提供酒精或乾洗手、狗便袋 協助清潔便溺物\n  設有動物友善公約"
  },
  {
    "Unnamed: 0":"中正區",
    "空間數":20.0,
    "業者名稱":"Take out新生店",
    "門市電話":"2321-0020",
    "業別":"餐飲業",
    "地址":"中正區新生南路一段56巷6號",
    "友善物種":"犬 (大\/中\/小型)、貓",
    "入內規定":"可落地\n  於提籠\/推車內才能進入（貓）",
    "提供寵物周邊服務":"寵物飲水",
    "環境服務":"無"
  },
  {
    "Unnamed: 0":"中正區",
    "空間數":21.0,
    "業者名稱":"渝廚娘",
    "門市電話":"02-82280756",
    "業別":"餐飲業",
    "地址":"中正區忠孝西路一段47號(K區地下街)",
    "友善物種":"犬 (中型)",
    "入內規定":"需全程繫牽繩",
    "提供寵物周邊服務":"廣場提供寵物飲水",
    "環境服務":"提供酒精或乾洗手"
  },
  {
    "Unnamed: 0":"中正區",
    "空間數":22.0,
    "業者名稱":"點8號",
    "門市電話":"02-29400528",
    "業別":"餐飲業",
    "地址":"中正區忠孝西路一段47號(K區地下街)",
    "友善物種":"貓",
    "入內規定":"於提籠\/推車內才能進入",
    "提供寵物周邊服務":"廣場提供寵物飲水",
    "環境服務":"提供酒精或乾洗手"
  },
  {
    "Unnamed: 0":"中正區",
    "空間數":23.0,
    "業者名稱":"PG美人網",
    "門市電話":"0906-157393",
    "業別":"百貨業",
    "地址":"中正區忠孝西路一段47號(K區地下街)",
    "友善物種":"貓",
    "入內規定":"於提籠\/推車內才能進入",
    "提供寵物周邊服務":"廣場提供寵物飲水",
    "環境服務":"提供酒精或乾洗手"
  },
  {
    "Unnamed: 0":"中正區",
    "空間數":24.0,
    "業者名稱":"QB HOUSE",
    "門市電話":"0-25589119",
    "業別":"美容業",
    "地址":"中正區忠孝西路一段47號(K區地下街)",
    "友善物種":"犬 (小型)",
    "入內規定":"於提籠\/推車內才能進入",
    "提供寵物周邊服務":"無",
    "環境服務":"提供酒精或乾洗手"
  },
  {
    "Unnamed: 0":"中正區",
    "空間數":25.0,
    "業者名稱":"喜寶棧咖啡酒館＆貓旅館.HIPP CAFE＆CATEL",
    "門市電話":"23035540",
    "業別":"餐飲業",
    "地址":"中正區中華路二段307巷40號1樓",
    "友善物種":"犬 (小型)、 貓",
    "入內規定":"可落地需繫牽繩",
    "提供寵物周邊服務":"提供寵物飲水",
    "環境服務":"提供酒精或乾洗手"
  },
  {
    "Unnamed: 0":"中正區",
    "空間數":26.0,
    "業者名稱":"TUTUKAKI司康小売所",
    "門市電話":"225676085",
    "業別":"餐飲業",
    "地址":"台北市中正區林森北路9巷23-1號",
    "友善物種":"家犬，大型(>23公斤), 家犬，中型(9-23公斤), 家犬，小型(<9公斤), 家貓",
    "入內規定":"可落地",
    "提供寵物周邊服務":"提供寵物飲水",
    "環境服務":"提供酒精或乾洗手"
  },
  {
    "Unnamed: 0":"北投區",
    "空間數":1.0,
    "業者名稱":"溫泉小舖",
    "門市電話":"2898-2698",
    "業別":"一般零售業",
    "地址":"北投區大同街202-4號1樓",
    "友善物種":"犬 (小型)、 貓",
    "入內規定":"可落地，需禮貌帶\/生理褲",
    "提供寵物周邊服務":"提供寵物飲用水，寵物用品販售",
    "環境服務":"提供酒精或乾洗手"
  },
  {
    "Unnamed: 0":"北投區",
    "空間數":2.0,
    "業者名稱":"故鄉農園",
    "門市電話":"0919-931-239",
    "業別":"餐飲業",
    "地址":"北投區⽵⼦湖路57之2號下150公尺(故鄉餐廳)",
    "友善物種":"犬 (大\/中\/小型)、貓",
    "入內規定":"可落地, 於提籠\/推車內才能進入, \n  一定要著禮貌帶\/生理褲, 不能隨地大小便\n  需服務人員帶位\n  如聲音過大需至餐廳外桌休息",
    "提供寵物周邊服務":"提供寵物飲水",
    "環境服務":"提供酒精或乾洗手"
  },
  {
    "Unnamed: 0":"北投區",
    "空間數":3.0,
    "業者名稱":"拖鞋咖啡Slipper Cafe",
    "門市電話":"2898-4520",
    "業別":"餐飲業",
    "地址":"北投區大同街15號",
    "友善物種":"犬 (大\/中\/小型)、貓",
    "入內規定":"需牽繩才可落地, 於提籠\/推車內才能進入",
    "提供寵物周邊服務":"提供寵物飲水, 寵物餐",
    "環境服務":"提供酒精或乾洗手"
  },
  {
    "Unnamed: 0":"北投區",
    "空間數":4.0,
    "業者名稱":"爐鍋咖啡館",
    "門市電話":"2891-5990",
    "業別":"餐飲業",
    "地址":"北投區大度路三段296巷39號",
    "友善物種":"犬 (大\/中\/小型)、貓",
    "入內規定":"可落地",
    "提供寵物周邊服務":"提供寵物飲水",
    "環境服務":"提供酒精或乾洗手"
  },
  {
    "Unnamed: 0":"北投區",
    "空間數":5.0,
    "業者名稱":"拾米屋",
    "門市電話":"2892-2800",
    "業別":"餐飲業",
    "地址":"北投區大同街153號",
    "友善物種":"犬 (中\/小型)、貓",
    "入內規定":"可落地, 於提籠\/推車內才能進入",
    "提供寵物周邊服務":"提供寵物飲水",
    "環境服務":"提供酒精或乾洗手"
  },
  {
    "Unnamed: 0":"北投區",
    "空間數":6.0,
    "業者名稱":"ㄉㄧㄢˇㄉㄧㄢ",
    "門市電話":"0972-337-556",
    "業別":"餐飲業",
    "地址":"北投區珠海路五號一樓",
    "友善物種":"犬 (中\/小型)、貓",
    "入內規定":"可落地, 於提籠\/推車內才能進入, 務必有牽繩",
    "提供寵物周邊服務":"提供寵物飲水",
    "環境服務":"提供酒精或乾洗手"
  },
  {
    "Unnamed: 0":"北投區",
    "空間數":7.0,
    "業者名稱":"WOYAO Burger",
    "門市電話":"0966-704-111",
    "業別":"餐飲業",
    "地址":"北投區大度路三段296巷46號1樓",
    "友善物種":"犬 (中\/小型)、貓",
    "入內規定":"無限制",
    "提供寵物周邊服務":"提供寵物飲水",
    "環境服務":"提供酒精或乾洗手"
  },
  {
    "Unnamed: 0":"北投區",
    "空間數":8.0,
    "業者名稱":"創義麵 石牌店",
    "門市電話":"02-2821-8567",
    "業別":"餐飲業",
    "地址":"北投區石牌路二段88號",
    "友善物種":"犬 (中\/小型)、貓",
    "入內規定":"可落地, 於提籠\/推車內能進入, 需全程繫牽繩",
    "提供寵物周邊服務":"提供寵物飲水, 寵物餐",
    "環境服務":"提供酒精或乾洗手"
  },
  {
    "Unnamed: 0":"北投區",
    "空間數":9.0,
    "業者名稱":"無眠workshop",
    "門市電話":"02-2894-0720",
    "業別":"餐飲業",
    "地址":"北投區復興四路22號",
    "友善物種":"犬 (中\/小型)、貓",
    "入內規定":"可落地, 於提籠\/推車內能進入, 需全程繫牽繩",
    "提供寵物周邊服務":"提供寵物飲水, 需自備寵物餐具",
    "環境服務":"提供酒精或乾洗手"
  },
  {
    "Unnamed: 0":"北投區",
    "空間數":10.0,
    "業者名稱":"1975 Antique’s Cafe Tea Room",
    "門市電話":"02-2897-6885",
    "業別":"餐飲業",
    "地址":"北投區大業路719號之一",
    "友善物種":"犬 (大\/中\/小型)、貓",
    "入內規定":"可落地, 一定要著禮貌帶\/生理褲",
    "提供寵物周邊服務":"提供寵物飲水",
    "環境服務":"提供酒精或乾洗手"
  },
  {
    "Unnamed: 0":"北投區",
    "空間數":11.0,
    "業者名稱":"獨木舟日常",
    "門市電話":"0915-137-829",
    "業別":"服務業",
    "地址":"北投區河美街32-8號",
    "友善物種":"犬 (大\/中\/小型)、貓",
    "入內規定":"需自備寵物救生衣",
    "提供寵物周邊服務":"提供寵物奔跑空間",
    "環境服務":"設有戶外簡易水管提供沖洗"
  },
  {
    "Unnamed: 0":"北投區",
    "空間數":12.0,
    "業者名稱":"海絲迪亞廚房",
    "門市電話":"02-2891-7200",
    "業別":"餐飲業",
    "地址":"北投區中正街64號",
    "友善物種":"犬 (大\/中\/小型)、貓",
    "入內規定":"可落地, 於提籠\/推車內能進入, 需全程繫牽繩, 不怕貓，可受控",
    "提供寵物周邊服務":"提供寵物飲水",
    "環境服務":"提供酒精或乾洗手"
  },
  {
    "Unnamed: 0":"北投區",
    "空間數":13.0,
    "業者名稱":"80後碼頭",
    "門市電話":"02-28943860",
    "業別":"餐飲業",
    "地址":"北投區中央北路二段68之5號1樓",
    "友善物種":"犬 (大\/中\/小型)、貓",
    "入內規定":"可落地, 於提籠\/推車內能進入, 不影響其他客人",
    "提供寵物周邊服務":"提供寵物飲水, 小量寵物玩具 沒其他客人時可解繩",
    "環境服務":"提供酒精或乾洗手"
  },
  {
    "Unnamed: 0":"內湖區",
    "空間數":1.0,
    "業者名稱":"兔兔日子 Tu's Day",
    "門市電話":"2799-7311",
    "業別":"餐飲業",
    "地址":"內湖區內湖路一段387巷3弄7號",
    "友善物種":"犬 (大\/中\/小型)、貓\n 非貓犬(無攻擊性者皆可)",
    "入內規定":"寵物可自由活動",
    "提供寵物周邊服務":"提供寵物飲用水",
    "環境服務":"提供酒精或乾洗手\n 協助清潔便溺物\n 提供狗便袋"
  },
  {
    "Unnamed: 0":"內湖區",
    "空間數":2.0,
    "業者名稱":"貳樓Second Floor Cafe-西湖店",
    "門市電話":"2799-7922",
    "業別":"餐飲業",
    "地址":"內湖區內湖路一段300號",
    "友善物種":"犬 (大\/中\/小型)、貓",
    "入內規定":"可落地",
    "提供寵物周邊服務":"免費提供寵物食用軟熟蛋",
    "環境服務":"提供紙巾與酒精供飼主做便溺清潔、寵物離店後將\n  加強該座位之清潔，下一位顧客可安心使用"
  },
  {
    "Unnamed: 0":"內湖區",
    "空間數":3.0,
    "業者名稱":"HOLA-內湖店",
    "門市電話":"8791-5566",
    "業別":"一般零售業",
    "地址":"內湖區新湖三路23號",
    "友善物種":"犬 (大\/中\/小型)、貓",
    "入內規定":"不可落地，需於寵物推車內",
    "提供寵物周邊服務":"提供寵物推車",
    "環境服務":"提供酒精或乾洗手\n  協助清潔便溺物\n  提供尿布墊"
  },
  {
    "Unnamed: 0":"內湖區",
    "空間數":4.0,
    "業者名稱":"特力屋-內湖店",
    "門市電話":"8791-8896",
    "業別":"一般零售業",
    "地址":"內湖區新湖三路23號地下一樓",
    "友善物種":"犬 (大\/中\/小型)、貓",
    "入內規定":"不可落地：\n  需有適當防護措施\n  (牽繩、揹袋、寵物推車或以手抱持)",
    "提供寵物周邊服務":"提供寵物推車、尿布墊",
    "環境服務":"提供酒精或乾洗手"
  },
  {
    "Unnamed: 0":"內湖區",
    "空間數":5.0,
    "業者名稱":"歐萊德流通股份有限公司 (ALL RIDE)",
    "門市電話":"7721-5668",
    "業別":"一般零售業",
    "地址":"臺北市內湖區洲子街71號",
    "友善物種":"犬 (大\/中\/小型)、貓",
    "入內規定":"可落地",
    "提供寵物周邊服務":null,
    "環境服務":"提供酒精或乾洗手\n  提供協助清潔便溺物"
  },
  {
    "Unnamed: 0":"內湖區",
    "空間數":6.0,
    "業者名稱":"金鍋盃內湖店",
    "門市電話":"8797-3827",
    "業別":"餐飲業",
    "地址":"內湖區環山路二段37號",
    "友善物種":"犬 (大\/中\/小型)、貓",
    "入內規定":"可落地，不可上桌",
    "提供寵物周邊服務":"提供寵物專用餐具，免費狗狗肉片",
    "環境服務":"提供酒精或乾洗手\n  提供狗便袋"
  },
  {
    "Unnamed: 0":"內湖區",
    "空間數":7.0,
    "業者名稱":"金烤盃",
    "門市電話":"2659-1212",
    "業別":"餐飲業",
    "地址":"內湖區江南街96巷7號1樓",
    "友善物種":"犬 (大\/中\/小型)、貓",
    "入內規定":"可落地：需著禮貌帶\/生理褲",
    "提供寵物周邊服務":"提供寵物餐\n  寵物專用餐具\n  防汙墊\n  提供寵物飲水與零食",
    "環境服務":"提供酒精或乾洗手\n  協助清潔便溺物\n  提供狗便袋"
  },
  {
    "Unnamed: 0":"內湖區",
    "空間數":8.0,
    "業者名稱":"白菜小姐義式坊",
    "門市電話":"2659-9066",
    "業別":"餐飲業",
    "地址":"內湖區江南街71巷16弄40號",
    "友善物種":"犬 (大\/中\/小型)、貓、其他寵物都歡迎",
    "入內規定":"可落地",
    "提供寵物周邊服務":"寵物奔跑空間",
    "環境服務":"提供酒精或乾洗手\n  協助清潔便溺物\n  提供狗便袋"
  },
  {
    "Unnamed: 0":"內湖區",
    "空間數":9.0,
    "業者名稱":"福容燒肉丼",
    "門市電話":"0905-303-054",
    "業別":"餐飲業",
    "地址":"內湖區康寧路三段219巷2號",
    "友善物種":"犬 (中\/小型)、貓",
    "入內規定":"可落地(不影響他人用餐即可)",
    "提供寵物周邊服務":"提供寵物飲水",
    "環境服務":"提供酒精或乾洗手"
  },
  {
    "Unnamed: 0":"內湖區",
    "空間數":10.0,
    "業者名稱":"金咼涮涮鍋",
    "門市電話":"2627-6327",
    "業別":"餐飲業",
    "地址":"內湖區港墘路108號",
    "友善物種":"犬 (小型)",
    "入內規定":"於提籠\/推車內才能進入(客人多時請依指定座位入座)",
    "提供寵物周邊服務":"提供寵物飲水、防汙墊",
    "環境服務":"提供酒精或乾洗手"
  },
  {
    "Unnamed: 0":"內湖區",
    "空間數":11.0,
    "業者名稱":"寵愛國際股份有限公司",
    "門市電話":"2797-2097",
    "業別":"其他教育",
    "地址":"內湖區環山路二段141號1樓",
    "友善物種":"犬(大\/中\/小型)、貓",
    "入內規定":"可落地, 一定要著禮貌帶\/生理褲",
    "提供寵物周邊服務":"提供寵物飲水, 寵物餐, 寵物專用餐具, 寵物床墊, 寵物用品販售, 寵\n  物奔跑空間\n  \"",
    "環境服務":"提供酒精或乾洗手, 協助清潔便溺物"
  },
  {
    "Unnamed: 0":"內湖區",
    "空間數":12.0,
    "業者名稱":"陽光廚坊",
    "門市電話":"2658-5559",
    "業別":"餐飲業",
    "地址":"內湖區環山路三段3號",
    "友善物種":"犬(小型)、 貓",
    "入內規定":"可落地",
    "提供寵物周邊服務":"提供寵物飲水",
    "環境服務":"提供酒精或乾洗手"
  },
  {
    "Unnamed: 0":"內湖區",
    "空間數":13.0,
    "業者名稱":"早樂子手作早午餐",
    "門市電話":"2793-9097",
    "業別":"餐飲業",
    "地址":"內湖區金龍路220號",
    "友善物種":"犬(大\/中\/小型)、貓",
    "入內規定":"可落地",
    "提供寵物周邊服務":"提供寵物飲水",
    "環境服務":"提供酒精或乾洗手"
  },
  {
    "Unnamed: 0":"內湖區",
    "空間數":14.0,
    "業者名稱":"克爾咖啡內湖店",
    "門市電話":"0986-361-168",
    "業別":"餐飲業",
    "地址":"內湖區港墘路127巷12號1樓",
    "友善物種":"犬(大\/中\/小型)",
    "入內規定":"可落地, 需全程繫牽繩",
    "提供寵物周邊服務":"提供寵物飲水, 防汙墊",
    "環境服務":"提供酒精或乾洗手"
  },
  {
    "Unnamed: 0":"內湖區",
    "空間數":15.0,
    "業者名稱":"森林善意廚房 內湖店",
    "門市電話":"971055850",
    "業別":"餐飲業",
    "地址":"內湖區瑞光路279號",
    "友善物種":"犬(大\/中\/小型)、貓",
    "入內規定":"無限制",
    "提供寵物周邊服務":"提供寵物飲水",
    "環境服務":"提供酒精或乾洗手, 提供狗便袋"
  },
  {
    "Unnamed: 0":"內湖區",
    "空間數":16.0,
    "業者名稱":"創義麵 東湖店",
    "門市電話":"02-2633-8399",
    "業別":"餐飲業",
    "地址":"內湖區東湖路119巷10號",
    "友善物種":"犬 (大\/中\/小型)、貓",
    "入內規定":"可落地, 於提籠\/推車內能進入, 需全程繫牽繩",
    "提供寵物周邊服務":"提供寵物飲水, 寵物餐",
    "環境服務":"提供酒精或乾洗手"
  },
  {
    "Unnamed: 0":"內湖區",
    "空間數":17.0,
    "業者名稱":"台北保時捷中心",
    "門市電話":"02-2799-8911",
    "業別":"一般零售業",
    "地址":"內湖區石潭路88號",
    "友善物種":"犬(大\/中\/小型)、貓",
    "入內規定":"無限制",
    "提供寵物周邊服務":"提供寵物飲水",
    "環境服務":"提供酒精或乾洗手"
  },
  {
    "Unnamed: 0":"內湖區",
    "空間數":18.0,
    "業者名稱":"伍食 No.510",
    "門市電話":"226335677",
    "業別":"餐飲業",
    "地址":"內湖區東湖路43巷26弄7號1樓",
    "友善物種":"犬(中\/小型)、貓",
    "入內規定":"可落地, 需全程繫牽繩, 一定要著禮貌帶\/生理褲",
    "提供寵物周邊服務":"提供寵物飲水, 防汙墊",
    "環境服務":"提供酒精或乾洗手"
  },
  {
    "Unnamed: 0":"內湖區",
    "空間數":19.0,
    "業者名稱":"李記甜品",
    "門市電話":"226580144",
    "業別":"餐飲業",
    "地址":"台北市內湖區江南街123號",
    "友善物種":"犬(大\/中\/小型)、貓",
    "入內規定":"無限制, 可落地",
    "提供寵物周邊服務":"提供寵物飲水",
    "環境服務":"提供酒精或乾洗手"
  },
  {
    "Unnamed: 0":"內湖區",
    "空間數":20.0,
    "業者名稱":"西湖市場",
    "門市電話":"226335679",
    "業別":"餐飲業",
    "地址":"台北市內湖區內湖路一段285號",
    "友善物種":"犬(大\/中\/小型)、貓",
    "入內規定":"無限制, 可落地",
    "提供寵物周邊服務":"無",
    "環境服務":"提供酒精或乾洗手"
  },
  {
    "Unnamed: 0":"南港區",
    "空間數":1.0,
    "業者名稱":"貳樓Second Floor Café-南港店",
    "門市電話":"2652-9168",
    "業別":"餐飲業",
    "地址":"南港區忠孝東路七段359號(南港車站B2棟2樓)",
    "友善物種":"犬 (大\/中\/小型)、貓",
    "入內規定":"可落地：無特別規定，但不可以亂跑、亂叫或隨地便溺",
    "提供寵物周邊服務":"提供寵物飲水",
    "環境服務":"提供酒精或乾洗手, 提供狗便袋"
  },
  {
    "Unnamed: 0":"南港區",
    "空間數":2.0,
    "業者名稱":"SHAIOOO CAFE",
    "門市電話":"2783-8860",
    "業別":"餐飲業",
    "地址":"南港區昆陽街140巷21號",
    "友善物種":"犬 (大\/中\/小型)、貓",
    "入內規定":"可落地：需著禮貌帶\/生理褲",
    "提供寵物周邊服務":"免費提供寵物飲水\n  提供軟熟蛋1份",
    "環境服務":"提供酒精或乾洗手"
  },
  {
    "Unnamed: 0":"南港區",
    "空間數":3.0,
    "業者名稱":"苒冉小食光",
    "門市電話":"2788-9639",
    "業別":"餐飲業",
    "地址":"南港區興中路28巷5號1樓",
    "友善物種":"犬 (大\/中\/小型)、貓",
    "入內規定":"可落地, 一定要著禮貌帶\/生理褲, 牽繩",
    "提供寵物周邊服務":"寵物奔跑空間",
    "環境服務":"提供酒精或乾洗手"
  },
  {
    "Unnamed: 0":"南港區",
    "空間數":4.0,
    "業者名稱":"Hungry Dogs 二犬廚房",
    "門市電話":"0937-037-702",
    "業別":"餐飲業",
    "地址":"南港區興中路44巷28號1樓",
    "友善物種":"犬 (大\/中\/小型)、貓",
    "入內規定":"可落地",
    "提供寵物周邊服務":"提供寵物飲水",
    "環境服務":"提供酒精或乾洗手"
  },
  {
    "Unnamed: 0":"南港區",
    "空間數":5.0,
    "業者名稱":"涓邸居酒屋",
    "門市電話":"2783-2022",
    "業別":"餐飲業",
    "地址":"南港區三重路32巷8號",
    "友善物種":"犬 (大\/中\/小型)、貓",
    "入內規定":null,
    "提供寵物周邊服務":"提供寵物飲水",
    "環境服務":"提供酒精或乾洗手"
  },
  {
    "Unnamed: 0":"南港區",
    "空間數":6.0,
    "業者名稱":"撲囉咖啡廳",
    "門市電話":"2788-8183",
    "業別":"餐飲業",
    "地址":"南港區經貿二路255巷33號",
    "友善物種":"犬 (大\/中\/小型)、貓、皆可",
    "入內規定":"可落地",
    "提供寵物周邊服務":"提供寵物飲水",
    "環境服務":"提供酒精或乾洗手"
  },
  {
    "Unnamed: 0":"南港區",
    "空間數":7.0,
    "業者名稱":"咕咕咕嚕",
    "門市電話":"2786-2529",
    "業別":"餐飲業",
    "地址":"南港區研究院路一段117號",
    "友善物種":"犬 (大\/中\/小型)",
    "入內規定":"可落地",
    "提供寵物周邊服務":"提供寵物飲水、寵物用品販售",
    "環境服務":"提供酒精或乾洗手"
  },
  {
    "Unnamed: 0":"南港區",
    "空間數":8.0,
    "業者名稱":"宇啡商行Real café",
    "門市電話":"2653-2693",
    "業別":"餐飲業",
    "地址":"南港區南港路一段43號",
    "友善物種":"犬 (大\/中\/小型)、貓",
    "入內規定":"可落地, 於提籠\/推車內才能進入, 一定要著禮貌帶\/生理褲",
    "提供寵物周邊服務":"寵物奔跑空間",
    "環境服務":"提供酒精或乾洗手"
  },
  {
    "Unnamed: 0":"南港區",
    "空間數":9.0,
    "業者名稱":"陶膳日本料理",
    "門市電話":"2651-1008",
    "業別":"餐飲業",
    "地址":"南港區園區街20號1樓",
    "友善物種":"犬 (大\/中\/小型)、貓",
    "入內規定":"可落地",
    "提供寵物周邊服務":"提供寵物飲水",
    "環境服務":"提供酒精或乾洗手"
  },
  {
    "Unnamed: 0":"南港區",
    "空間數":10.0,
    "業者名稱":"TUMAZ COFFEE",
    "門市電話":"2651-1664",
    "業別":"餐飲業",
    "地址":"南港區重陽路561號",
    "友善物種":"犬 (大\/中\/小型)、貓",
    "入內規定":"可落地, 於提籠\/推車內或繫牽繩才能進入（固定在座位不影響到其他客人）",
    "提供寵物周邊服務":"提供寵物飲水、寵物餐、防汙墊",
    "環境服務":"提供酒精或乾洗手"
  },
  {
    "Unnamed: 0":"南港區",
    "空間數":11.0,
    "業者名稱":"台北六福萬怡酒店-寵物專屬客房",
    "門市電話":"2171-6565",
    "業別":"住宿業",
    "地址":"南港區忠孝東路七段359號7樓",
    "友善物種":"犬 (30公斤以下)、貓",
    "入內規定":"於提籠\/推車內才能進入",
    "提供寵物周邊服務":"提供寵物飲水、防汙墊",
    "環境服務":"提供酒精或乾洗手"
  },
  {
    "Unnamed: 0":"南港區",
    "空間數":12.0,
    "業者名稱":"大山昆陽咖啡",
    "門市電話":"2785-2836",
    "業別":"餐飲業",
    "地址":"南港區昆陽街140巷17號",
    "友善物種":"犬 (大\/中\/小型)、貓",
    "入內規定":"無限制",
    "提供寵物周邊服務":"提供寵物餐、寵物專用餐具、寵物床墊、防汙墊、寵物奔跑空間。",
    "環境服務":"提供酒精或乾洗手"
  },
  {
    "Unnamed: 0":"南港區",
    "空間數":13.0,
    "業者名稱":"飲飽食醉餐廳",
    "門市電話":"02-27827076",
    "業別":"餐飲業",
    "地址":"南港區研究院路2段25號",
    "友善物種":"犬 (大\/中\/小型)、貓",
    "入內規定":"無限制",
    "提供寵物周邊服務":"提供寵物飲水",
    "環境服務":"提供酒精或乾洗手, 協助清潔便溺物, 提供狗便袋"
  },
  {
    "Unnamed: 0":"中山區",
    "空間數":1.0,
    "業者名稱":"神農市場-花博門市",
    "門市電話":"2597-7112",
    "業別":"一般零售業",
    "地址":"中山區玉門街1號",
    "友善物種":"犬 (大\/中\/小型)、貓",
    "入內規定":"於提籠\/推車內或以手抱持才能進入",
    "提供寵物周邊服務":"提供寵物飲水",
    "環境服務":"提供酒精或乾洗手"
  },
  {
    "Unnamed: 0":"中山區",
    "空間數":2.0,
    "業者名稱":"邦尼是個星球 寵物攝影",
    "門市電話":"2541-6133",
    "業別":"其他-寵物攝影",
    "地址":"中山區民權東路三段7號2樓",
    "友善物種":"犬 (大\/中\/小型)、貓、兔子",
    "入內規定":"可落地",
    "提供寵物周邊服務":"無",
    "環境服務":"提供酒精或乾洗手"
  },
  {
    "Unnamed: 0":"中山區",
    "空間數":3.0,
    "業者名稱":"House cafe",
    "門市電話":"2599-7058",
    "業別":"餐飲業",
    "地址":"中山區德惠街4號1樓",
    "友善物種":"犬 (大\/中\/小型)、貓",
    "入內規定":"可落地",
    "提供寵物周邊服務":"提供奔跑空間",
    "環境服務":"提供酒精或乾洗手\n  提供協助清潔便溺物"
  },
  {
    "Unnamed: 0":"中山區",
    "空間數":4.0,
    "業者名稱":"Escapeholics密室逃脫",
    "門市電話":"2595-5760",
    "業別":"其他-遊戲場館",
    "地址":"中山區農安街19號B1",
    "友善物種":"犬 (大\/中\/小型)、貓",
    "入內規定":"可落地\n  請穿禮貌帶∕生理褲",
    "提供寵物周邊服務":"寵物專用餐具\n  提供寵物禮貌帶\n  寵物餐\n  寵物用品販售\n  寵物奔跑空間",
    "環境服務":"提供酒精或乾洗手 \n  提供狗便袋 \n  協助清潔便溺物\n  其他：生日、包場"
  },
  {
    "Unnamed: 0":"中山區",
    "空間數":5.0,
    "業者名稱":"毛時光出租空間",
    "門市電話":"2571-8425",
    "業別":"其他",
    "地址":"中山區吉林路26巷26號",
    "友善物種":"犬 (大\/中\/小型)、貓\n  其他：任何動物",
    "入內規定":"可落地\n  請穿禮貌帶∕生理褲\n  店內設有動物友善公約",
    "提供寵物周邊服務":"寵物飲水",
    "環境服務":"無"
  },
  {
    "Unnamed: 0":"中山區",
    "空間數":6.0,
    "業者名稱":"MAJI集食行樂",
    "門市電話":"2597-7112",
    "業別":"一般零售業",
    "地址":"中山區玉門街1號",
    "友善物種":"犬 (大\/中\/小型)、貓",
    "入內規定":"可落地",
    "提供寵物周邊服務":"寵物奔跑空間、寵物飲水",
    "環境服務":"提供酒精或乾洗手"
  },
  {
    "Unnamed: 0":"中山區",
    "空間數":7.0,
    "業者名稱":"面對面Face to Face Noodle House",
    "門市電話":"2517-1517",
    "業別":"餐飲業",
    "地址":"中山區錦州街310號",
    "友善物種":"犬 (大\/中\/小型)、貓",
    "入內規定":"可落地",
    "提供寵物周邊服務":"提供飲水",
    "環境服務":"協助清潔便溺物"
  },
  {
    "Unnamed: 0":"中山區",
    "空間數":8.0,
    "業者名稱":"父母 - FuMu",
    "門市電話":"2518-5660",
    "業別":"餐飲業",
    "地址":"中山區興安街103號",
    "友善物種":"犬 (大\/中\/小型)、貓",
    "入內規定":"可落地，需綁牽繩",
    "提供寵物周邊服務":"寵物飲水",
    "環境服務":"提供酒精或乾洗手"
  },
  {
    "Unnamed: 0":"中山區",
    "空間數":9.0,
    "業者名稱":"TUTUKAKI 司康小売所",
    "門市電話":"2567-6085",
    "業別":"餐飲業",
    "地址":"中山區中山北路二段26巷3號",
    "友善物種":"犬 (大\/中\/小型)、其他動物",
    "入內規定":"可落地, 需有牽繩",
    "提供寵物周邊服務":"寵物飲水",
    "環境服務":"無"
  },
  {
    "Unnamed: 0":"中山區",
    "空間數":10.0,
    "業者名稱":"富氣水產",
    "門市電話":"2740-8641",
    "業別":"餐飲業",
    "地址":"中山區遼寧街57號",
    "友善物種":"犬 (中\/小型)、貓",
    "入內規定":"於提籠\/推車內才能進入",
    "提供寵物周邊服務":"寵物餐, 寵物專用餐具",
    "環境服務":"無"
  },
  {
    "Unnamed: 0":"中山區",
    "空間數":11.0,
    "業者名稱":"紅記珠寶",
    "門市電話":"2523-0122",
    "業別":"一般零售業",
    "地址":"中山區林森北路109號1樓",
    "友善物種":"犬 (大\/中\/小型)、貓",
    "入內規定":"於提籠\/推車內才能進入, 一定要著禮貌帶\/生理褲",
    "提供寵物周邊服務":"提供寵物飲水",
    "環境服務":"提供酒精或乾洗手"
  },
  {
    "Unnamed: 0":"中山區",
    "空間數":12.0,
    "業者名稱":"誠意中西藥局",
    "門市電話":"2595-0951",
    "業別":"其他-藥局",
    "地址":"中山區林森北路613號",
    "友善物種":"犬 (大\/中\/小型)",
    "入內規定":"可落地, 需有牽繩",
    "提供寵物周邊服務":"提供寵物飲水",
    "環境服務":"提供酒精或乾洗手, 協助清潔便溺物, 提供狗便袋"
  },
  {
    "Unnamed: 0":"中山區",
    "空間數":13.0,
    "業者名稱":"工作樂共享空間",
    "門市電話":"6604-0699#8001",
    "業別":"其他-共享空間",
    "地址":"中山區松江路64巷10-2號2-3樓",
    "友善物種":"犬 (大\/中\/小型)、貓",
    "入內規定":"可落地",
    "提供寵物周邊服務":"提供寵物飲水, 寵物用品販售",
    "環境服務":"提供酒精或乾洗手"
  },
  {
    "Unnamed: 0":"中山區",
    "空間數":14.0,
    "業者名稱":"餘生漫漫",
    "門市電話":"6604-0699#8001",
    "業別":"餐飲業",
    "地址":"中山區松江路64巷10-2號1樓",
    "友善物種":"犬 (大\/中\/小型)、貓",
    "入內規定":"可落地",
    "提供寵物周邊服務":"提供寵物飲水",
    "環境服務":"提供酒精或乾洗手"
  },
  {
    "Unnamed: 0":"中山區",
    "空間數":15.0,
    "業者名稱":"嬉皮麵包",
    "門市電話":"2567-9969",
    "業別":"餐飲業",
    "地址":"中山區四平街7號",
    "友善物種":"犬 (大\/中\/小型)、貓",
    "入內規定":"可落地, 需有牽繩",
    "提供寵物周邊服務":"提供寵物飲水",
    "環境服務":"提供酒精或乾洗手"
  },
  {
    "Unnamed: 0":"中山區",
    "空間數":16.0,
    "業者名稱":"豐味亭異國素食餐廳",
    "門市電話":"02-25996000",
    "業別":"餐飲業",
    "地址":"台北市中山區雙城街3巷2號一樓",
    "友善物種":"犬 (大\/中\/小型)、貓",
    "入內規定":"無",
    "提供寵物周邊服務":"提供寵物飲水",
    "環境服務":"提供酒精或乾洗手"
  },
  {
    "Unnamed: 0":"中山區",
    "空間數":17.0,
    "業者名稱":"HBJ kitchen健康舒肥餐",
    "門市電話":"2741-3646",
    "業別":"餐飲業",
    "地址":"中山區龍江路21巷18號1樓",
    "友善物種":"犬 (中\/小型)、貓",
    "入內規定":"可落地, 需有牽繩",
    "提供寵物周邊服務":"提供寵物飲水",
    "環境服務":"提供酒精或乾洗手"
  },
  {
    "Unnamed: 0":"中山區",
    "空間數":18.0,
    "業者名稱":"Breakfirst Cafe&Studio",
    "門市電話":"2533-5648",
    "業別":"餐飲業",
    "地址":"中山區北安路573巷15號一樓",
    "友善物種":"犬 (大\/中\/小型)、貓",
    "入內規定":"可落地, 於提籠\/推車內才能進入, 一定要著禮貌帶\/生理褲",
    "提供寵物周邊服務":"提供寵物飲水",
    "環境服務":"提供酒精或乾洗手"
  },
  {
    "Unnamed: 0":"中山區",
    "空間數":19.0,
    "業者名稱":"東風饌麻辣燙大直店",
    "門市電話":"8502-3086",
    "業別":"餐飲業",
    "地址":"中山區樂群二路146號",
    "友善物種":"犬 (大\/中\/小型)、貓",
    "入內規定":"可落地",
    "提供寵物周邊服務":"提供寵物飲水 設有寵物友善公約並張貼於明顯處",
    "環境服務":"提供酒精或乾洗手"
  },
  {
    "Unnamed: 0":"中山區",
    "空間數":20.0,
    "業者名稱":"旭牧高纖沙拉輕食-台北松江店",
    "門市電話":"2521-5122",
    "業別":"餐飲業",
    "地址":"中山區松江路100巷27號1樓",
    "友善物種":"犬 (大\/中\/小型)",
    "入內規定":"可落地",
    "提供寵物周邊服務":"提供寵物飲水",
    "環境服務":"提供酒精或乾洗手, 協助清潔便溺物"
  },
  {
    "Unnamed: 0":"中山區",
    "空間數":21.0,
    "業者名稱":"CHOiCE Gelato義式手工冰淇淋",
    "門市電話":"2508-2508",
    "業別":"餐飲業",
    "地址":"中山區民權東路二段152巷5弄2號",
    "友善物種":"犬 (大\/中\/小型)、貓",
    "入內規定":"可落地",
    "提供寵物周邊服務":"提供寵物飲水、寵物餐",
    "環境服務":"提供酒精或乾洗手, 協助清潔便溺物, 提供狗便袋"
  },
  {
    "Unnamed: 0":"中山區",
    "空間數":22.0,
    "業者名稱":"勺日咖啡廳 忠泰樂生活店",
    "門市電話":"2508-2508",
    "業別":"餐飲業",
    "地址":"中山區樂群三路200號3樓",
    "友善物種":"犬 (大\/中\/小型)、貓、兔子、鳥",
    "入內規定":"於提籠\/推車內才能進入",
    "提供寵物周邊服務":"提供寵物飲水、寵物餐",
    "環境服務":"提供酒精或乾洗手, 協助清潔便溺物, 提供狗便袋"
  },
  {
    "Unnamed: 0":"中山區",
    "空間數":23.0,
    "業者名稱":"MUY 莯以咖啡",
    "門市電話":"0933-797-311",
    "業別":"餐飲業",
    "地址":"中山區民權東路二段135巷30弄20號1樓",
    "友善物種":"犬 (大\/中\/小型)、貓",
    "入內規定":"可落地, 寵物可上椅，但不可上桌；建議要著禮貌帶\/生理褲，若有便溺情形需付清潔費",
    "提供寵物周邊服務":"提供寵物飲水",
    "環境服務":"提供酒精或乾洗手, 協助清潔便溺物, 提供狗便袋"
  },
  {
    "Unnamed: 0":"中山區",
    "空間數":24.0,
    "業者名稱":"創義麵 錦州店",
    "門市電話":"02-25039123",
    "業別":"餐飲業",
    "地址":"中山區錦州街442號",
    "友善物種":"犬 (大\/中\/小型)、貓",
    "入內規定":"可落地, 於提籠\/推車內能進入, 需全程繫牽繩",
    "提供寵物周邊服務":"提供貓與狗的寵物零食，一隻提供一份",
    "環境服務":"提供酒精或乾洗手"
  },
  {
    "Unnamed: 0":"中山區",
    "空間數":25.0,
    "業者名稱":"千彩格精品旅店",
    "門市電話":"02-2563-7555",
    "業別":"住宿業",
    "地址":"中山區林森北路286號2樓、3樓",
    "友善物種":"犬 (大\/中\/小型)、貓",
    "入內規定":"可落地, 需全程繫牽繩",
    "提供寵物周邊服務":"提供寵物飲水",
    "環境服務":"提供酒精或乾洗手"
  },
  {
    "Unnamed: 0":"中山區",
    "空間數":26.0,
    "業者名稱":"青色髮廊 CYAN Hair Boutique",
    "門市電話":"02-225371066",
    "業別":"美容業",
    "地址":"中山區南京西路1-2號號7樓",
    "友善物種":"犬 (大\/中\/小型)、貓",
    "入內規定":"可落地",
    "提供寵物周邊服務":"提供寵物飲水, 寵物奔跑空間",
    "環境服務":"提供酒精或乾洗手, 提供狗便袋"
  },
  {
    "Unnamed: 0":"中山區",
    "空間數":27.0,
    "業者名稱":"小雲雲瑜珈配件",
    "門市電話":"02-26393022",
    "業別":"服飾業",
    "地址":"中山區錦州街157巷7號",
    "友善物種":"犬 (大\/中\/小型)、貓",
    "入內規定":"可落地, 於提籠\/推車內能進入, 需全程繫牽繩, 一定要著禮貌帶\/生理褲",
    "提供寵物周邊服務":"提供寵物飲水",
    "環境服務":"提供酒精或乾洗手"
  },
  {
    "Unnamed: 0":"中山區",
    "空間數":28.0,
    "業者名稱":"本願豆花店-晴光",
    "門市電話":"0928-052-001",
    "業別":"餐飲業",
    "地址":"中山區雙城街13巷32號",
    "友善物種":"犬 (大\/中\/小型)、貓",
    "入內規定":"可落地, 於提籠\/推車內能進入, 需全程繫牽繩, 一定要著禮貌帶\/生理褲",
    "提供寵物周邊服務":"提供寵物飲水",
    "環境服務":"提供酒精或乾洗手"
  },
  {
    "Unnamed: 0":"中山區",
    "空間數":29.0,
    "業者名稱":"練功房 The Pain Cave 運動訓練",
    "門市電話":"925105206",
    "業別":"競技及休閒運動場館業",
    "地址":"中山區林森北路612號2樓",
    "友善物種":"犬 (大\/中\/小型)、貓",
    "入內規定":"可落地, 不得進入草皮及地墊區域",
    "提供寵物周邊服務":"提供寵物飲水, 寵物奔跑空間",
    "環境服務":"提供酒精或乾洗手"
  },
  {
    "Unnamed: 0":"中山區",
    "空間數":30.0,
    "業者名稱":"DO菇 Brunch",
    "門市電話":"225322218",
    "業別":"餐飲業",
    "地址":"中山區北安路621巷12號",
    "友善物種":"犬 (大\/中\/小型)、貓",
    "入內規定":"有牽繩或推車即可入內落地",
    "提供寵物周邊服務":"提供寵物飲水",
    "環境服務":"提供酒精或乾洗手"
  },
  {
    "Unnamed: 0":"中山區",
    "空間數":31.0,
    "業者名稱":"一鷺炭火燒鳥工房 松江本店",
    "門市電話":"02-2507-9885",
    "業別":"餐飲業",
    "地址":"台北市中山區民權東路2段152巷1號",
    "友善物種":"家犬，大型(>23公斤), 家犬，中型(9-23公斤), 家犬，小型(<9公斤), 家貓",
    "入內規定":"可落地, 於提籠\/推車內能進入, 需全程繫牽繩",
    "提供寵物周邊服務":"提供寵物飲水, 寵物餐, 寵物專用餐具",
    "環境服務":"提供酒精或乾洗手, 協助清潔便溺物"
  },
  {
    "Unnamed: 0":"中山區",
    "空間數":32.0,
    "業者名稱":"一鷺炭火燒鳥工房 大直旗艦店",
    "門市電話":"966275853",
    "業別":"餐飲業",
    "地址":"台北市中山區植福路217號",
    "友善物種":"家犬，大型(>23公斤), 家犬，中型(9-23公斤), 家犬，小型(<9公斤), 家貓",
    "入內規定":"可落地, 於提籠\/推車內能進入, 需全程繫牽繩",
    "提供寵物周邊服務":"提供寵物飲水, 寵物餐, 寵物專用餐具",
    "環境服務":"提供酒精或乾洗手, 協助清潔便溺物, 提供狗便袋"
  },
  {
    "Unnamed: 0":null,
    "空間數":null,
    "業者名稱":null,
    "門市電話":null,
    "業別":null,
    "地址":null,
    "友善物種":null,
    "入內規定":null,
    "提供寵物周邊服務":null,
    "環境服務":null
  },
  {
    "Unnamed: 0":"交通運輸業者",
    "空間數":1.0,
    "業者名稱":"大都會客運-0東路線",
    "門市電話":"2976-2999",
    "業別":"交通運輸業-狗狗公車",
    "地址":"行經迎風狗運動公園",
    "友善物種":"犬 (大\/中\/小型)",
    "入內規定":"具適當防護措施(牽繩、揹袋、推車、以手抱持、推車及運輸籠內即可進入)\n  犬隻繫牽繩可落地\n  家犬免費搭乘",
    "提供寵物周邊服務":"提供寵物載運服務，行車路線行經狗運動公園或狗活動區",
    "環境服務":"無"
  },
  {
    "Unnamed: 0":"交通運輸業者",
    "空間數":2.0,
    "業者名稱":"欣欣客運-棕6路線",
    "門市電話":"2369-9696",
    "業別":"交通運輸業-狗狗公車",
    "地址":"行經萬興狗活動區",
    "友善物種":"犬 (大\/中\/小型)",
    "入內規定":null,
    "提供寵物周邊服務":null,
    "環境服務":null
  },
  {
    "Unnamed: 0":"交通運輸業者",
    "空間數":3.0,
    "業者名稱":"三重客運-225路線",
    "門市電話":"2988-2133",
    "業別":"交通運輸業-狗狗公車",
    "地址":"行經迎風狗運動公園",
    "友善物種":"犬 (大\/中\/小型)",
    "入內規定":null,
    "提供寵物周邊服務":null,
    "環境服務":null
  },
  {
    "Unnamed: 0":"交通運輸業者",
    "空間數":4.0,
    "業者名稱":"首都客運-669路線",
    "門市電話":"8972-1999",
    "業別":"交通運輸業-狗狗公車",
    "地址":"行經華山狗活動區、葫東狗狗活動區、延平狗活動區、信義廣場狗活動區",
    "友善物種":"犬 (大\/中\/小型)",
    "入內規定":null,
    "提供寵物周邊服務":null,
    "環境服務":null
  },
  {
    "Unnamed: 0":"交通運輸業者",
    "空間數":5.0,
    "業者名稱":"中興巴士-279路線",
    "門市電話":"2882-6780",
    "業別":"交通運輸業-狗狗公車",
    "地址":"行經潭美毛寶貝快樂公園",
    "友善物種":"犬 (大\/中\/小型)",
    "入內規定":null,
    "提供寵物周邊服務":null,
    "環境服務":null
  },
  {
    "Unnamed: 0":"交通運輸業者",
    "空間數":6.0,
    "業者名稱":"光華巴士-681路線",
    "門市電話":"2882-6780",
    "業別":"交通運輸業-狗狗公車",
    "地址":"行經潭美毛寶貝快樂公園 、至善公園(福林)狗狗活動區、北勢湖公園狗活動區",
    "友善物種":"犬 (大\/中\/小型)",
    "入內規定":null,
    "提供寵物周邊服務":null,
    "環境服務":null
  },
  {
    "Unnamed: 0":"交通運輸業者",
    "空間數":7.0,
    "業者名稱":"陳司機(346-C3)",
    "門市電話":"0933-821-739",
    "業別":"交通運輸業-個人計程車",
    "地址":"個人計程車行(北區，請事先打電話預約)\n  346-C3",
    "友善物種":"犬 (大\/中\/小型)、貓",
    "入內規定":"可落地",
    "提供寵物周邊服務":"無",
    "環境服務":"無"
  },
  {
    "Unnamed: 0":"交通運輸業者",
    "空間數":8.0,
    "業者名稱":"謝司機(562-P2)",
    "門市電話":"0935-207-830",
    "業別":"交通運輸業-個人計程車",
    "地址":"562-P2 (北區，請事先打電話預約)",
    "友善物種":"犬 (大\/中\/小型)、貓、其他",
    "入內規定":"可落地",
    "提供寵物周邊服務":"無",
    "環境服務":"無"
  },
  {
    "Unnamed: 0":"交通運輸業者",
    "空間數":9.0,
    "業者名稱":"大都會衛星車隊股份有限公司",
    "門市電話":"4499178",
    "業別":"交通運輸業-計程車車隊",
    "地址":"大都會衛星車隊",
    "友善物種":"犬 (大\/中\/小型)",
    "入內規定":"需個別詢問",
    "提供寵物周邊服務":null,
    "環境服務":null
  },
  {
    "Unnamed: 0":"交通運輸業者",
    "空間數":10.0,
    "業者名稱":"城市衛星(大愛. 婦協. 泛亞)",
    "門市電話":"55899",
    "業別":"交通運輸業-計程車車隊",
    "地址":"城市衛星(大愛. 婦協. 泛亞)",
    "友善物種":"犬 (大\/中\/小型)",
    "入內規定":"需個別詢問",
    "提供寵物周邊服務":null,
    "環境服務":null
  },
  {
    "Unnamed: 0":"交通運輸業者",
    "空間數":11.0,
    "業者名稱":"台灣大車隊股份有限公司",
    "門市電話":"55688",
    "業別":"交通運輸業-計程車車隊",
    "地址":"台灣大車隊",
    "友善物種":"犬 (大\/中\/小型)",
    "入內規定":"需個別詢問",
    "提供寵物周邊服務":null,
    "環境服務":null
  },
  {
    "Unnamed: 0":"交通運輸業者",
    "空間數":12.0,
    "業者名稱":"洪司機(TDP-0508)",
    "門市電話":"0987-057-397",
    "業別":"交通運輸業-個人計程車",
    "地址":"個人計程車",
    "友善物種":"犬 (大\/中\/小型)、貓、其他",
    "入內規定":"可落地\n  請穿禮貌帶∕生理褲 \n  一次僅服務一組客人，上車前請除蚤、備牽繩",
    "提供寵物周邊服務":"提供防汙墊(寵物看護墊及尿布墊)",
    "環境服務":"提供酒精或乾洗手、狗便袋"
  },
  {
    "Unnamed: 0":"交通運輸業者",
    "空間數":13.0,
    "業者名稱":"大都會客運-262區間路線",
    "門市電話":"0800-053-434",
    "業別":"交通運輸業-狗狗公車",
    "地址":"行經迎風狗運動公園",
    "友善物種":"犬 (大\/中\/小型)",
    "入內規定":"具適當防護措施(牽繩、揹袋、推車、以手抱持、推車及運輸籠內即可進入)\n  犬隻繫牽繩可落地\n  家犬免費搭乘",
    "提供寵物周邊服務":"提供寵物載運服務，行車路線行經狗運動公園或狗活動區",
    "環境服務":"無"
  },
  {
    "Unnamed: 0":"交通運輸業者",
    "空間數":14.0,
    "業者名稱":"光華巴士-620路線",
    "門市電話":"0800-002-277",
    "業別":"交通運輸業-狗狗公車",
    "地址":"行經潭美毛寶貝快樂公園、至善公園(福林)狗狗活動區、北勢湖公園狗活動區",
    "友善物種":"犬 (大\/中\/小型)",
    "入內規定":null,
    "提供寵物周邊服務":null,
    "環境服務":null
  },
  {
    "Unnamed: 0":"交通運輸業者",
    "空間數":15.0,
    "業者名稱":"大有巴士-620路線",
    "門市電話":"0800-088-626",
    "業別":"交通運輸業-狗狗公車",
    "地址":"行經潭美毛寶貝快樂公園、至善公園(福林)狗狗活動區、北勢湖公園狗活動區",
    "友善物種":"犬 (大\/中\/小型)",
    "入內規定":null,
    "提供寵物周邊服務":null,
    "環境服務":null
  },
  {
    "Unnamed: 0":"交通運輸業者",
    "空間數":16.0,
    "業者名稱":"大有巴士-257路線",
    "門市電話":"0800-088-626",
    "業別":"交通運輸業-狗狗公車",
    "地址":"行經華山公園狗活動區、玉成公園狗活動區",
    "友善物種":"犬 (大\/中\/小型)",
    "入內規定":null,
    "提供寵物周邊服務":null,
    "環境服務":null
  },
  {
    "Unnamed: 0":"交通運輸業者",
    "空間數":17.0,
    "業者名稱":"大南汽車-265路線",
    "門市電話":"0800-089-456",
    "業別":"交通運輸業-狗狗公車",
    "地址":"行經華山公園狗活動區",
    "友善物種":"犬 (大\/中\/小型)",
    "入內規定":null,
    "提供寵物周邊服務":null,
    "環境服務":null
  },
  {
    "Unnamed: 0":"交通運輸業者",
    "空間數":18.0,
    "業者名稱":"指南客運-679路線",
    "門市電話":"0800-002-279",
    "業別":"交通運輸業-狗狗公車",
    "地址":"行經萬興狗活動區",
    "友善物種":"犬 (大\/中\/小型)",
    "入內規定":null,
    "提供寵物周邊服務":null,
    "環境服務":null
  },
  {
    "Unnamed: 0":"交通運輸業者",
    "空間數":19.0,
    "業者名稱":"東南客運-207路線",
    "門市電話":"0800-616-688",
    "業別":"交通運輸業-狗狗公車",
    "地址":"行經玉成公園狗活動區、青峰狗活動區、信義廣場狗活動區",
    "友善物種":"犬 (大\/中\/小型)",
    "入內規定":null,
    "提供寵物周邊服務":null,
    "環境服務":null
  },
  {
    "Unnamed: 0":"交通運輸業者",
    "空間數":20.0,
    "業者名稱":"林司機(TDN-3581)",
    "門市電話":"0978-720-773",
    "業別":"交通運輸業-個人計程車",
    "地址":"個人計程車",
    "友善物種":"犬 (大\/中\/小型)、貓、其他",
    "入內規定":"可落地",
    "提供寵物周邊服務":"提供防汙墊",
    "環境服務":"提供酒精或乾洗手、狗便袋"
  },
  {
    "Unnamed: 0":"交通運輸業者",
    "空間數":21.0,
    "業者名稱":"欣欣客運-1路線",
    "門市電話":"0800-032-159",
    "業別":"交通運輸業-狗狗公車",
    "地址":"行經古亭狗活動區、華江狗活動區、青峰狗活動區",
    "友善物種":"犬 (大\/中\/小型)",
    "入內規定":"具適當防護措施(牽繩、揹袋、推車、以手抱持、推車及運輸籠內即可進入) 犬隻繫牽繩可落地 家犬免費搭乘",
    "提供寵物周邊服務":"提供寵物載運服務，行車路線行經狗運動公園或狗活動區",
    "環境服務":"無"
  },
  {
    "Unnamed: 0":"交通運輸業者",
    "空間數":22.0,
    "業者名稱":"指南客運-757路線",
    "門市電話":"0800-002-279",
    "業別":"交通運輸業-狗狗公車",
    "地址":"行經葫東狗活動區、洲美狗活動區、福順狗運動公園",
    "友善物種":"犬 (大\/中\/小型)",
    "入內規定":null,
    "提供寵物周邊服務":null,
    "環境服務":null
  },
  {
    "Unnamed: 0":"交通運輸業者",
    "空間數":23.0,
    "業者名稱":"大南汽車-302路線",
    "門市電話":"0800-089-456",
    "業別":"交通運輸業-狗狗公車",
    "地址":"行經葫東狗活動區、大同狗活動區",
    "友善物種":"犬 (大\/中\/小型)",
    "入內規定":null,
    "提供寵物周邊服務":null,
    "環境服務":null
  },
  {
    "Unnamed: 0":"交通運輸業者",
    "空間數":24.0,
    "業者名稱":"中興巴士-304承德線",
    "門市電話":"2882-6780",
    "業別":"交通運輸業-狗狗公車",
    "地址":"行經三腳渡狗狗活動區",
    "友善物種":"犬 (大\/中\/小型)",
    "入內規定":null,
    "提供寵物周邊服務":null,
    "環境服務":null
  }
]